Workbook

Sheet balance
C1: 2024.12.31 | D1: 2023.12.31 | E1: 2022.12.31 | F1: 2021.12.31 | G1: 2020.12.31 | H1: 2019.12.31 | I1: 2018.12.21 | J1: 2017.12.31 | K1: 2016.12.31 | L1: 2015.12.31
A2: 资产 | C2: =C4+C13+C25+C10 -> 63254182536 | D2: =D4+D13+D25+D10 -> 56630407495 | E2: =E4+E13+E25+E10 -> 50767498791 | F2: =F4+F13+F25+F10 -> 44784893954 | G2: =G4+G13+G25+G10 -> 38423625184 | H2: =H4+H13+H25+H10 -> 38826279607 | I2: =I4+I13+I25+I10 -> 34490438670 | J2: =J4+J13+J25+J10 -> 31920898046 | ... L2: =L4+L13+L25+L10 -> 24640919497
A4: 金融资产 | C4: =SUM(C5:C9) -> 20713712160 | D4: =SUM(D5:D9) -> 19838830944 | E4: =SUM(E5:E9) -> 18165180172 | F4: =SUM(F5:F9) -> 15447688808 | G4: =SUM(G5:G9) -> 10411885641 | H4: =SUM(H5:H9) -> 10001551003 | I4: =SUM(I5:I9) -> 6800777265 | J4: =SUM(J5:J9) -> 6833689446 | ... L4: =SUM(L5:L9) -> 5918845168
B5: 货币资金 | C5: 18784564004 | D5: 18518172689 | E5: 17019655848 | F5: 14327356262 | G5: 8809985853 | H5: 8356153735 | I5: 6365973126 | J5: 6728200042 | K5: 7211178987 | L5: 5918845168
B6: 交易性金融资产（权益工具、存款） | C6: 7682574 | D6: 5740618 | E6: 7396158 | F6: 6320181 | G6: 300287671 | H6: 860894383 | I6: 387261777 | J6: 101927854 | K6: 1951267
B7: 衍生金融资产 | H7: 85110 | I7: 47542362 | J7: 3561550
B8: 应收款项融资 | C8: 1921465582 | D8: 1314917637 | E8: 1138128166 | F8: 1114012365 | G8: 1301612117 | H8: 784417775
B9: 其他流动资产
A10: 长期股权资产 | C10: =SUM(C11:C12) -> 524177494 | D10: =SUM(D11:D12) -> 272592774 | E10: =SUM(E11:E12) -> 327607056 | F10: =SUM(F11:F12) -> 298144705 | G10: =SUM(G11:G12) -> 264748905 | H10: =SUM(H11:H12) -> 199805151 | I10: =SUM(I11:I12) -> 205738050 | J10: =SUM(J11:J12) -> 95519959 | ... L10: =SUM(L11:L12) -> 46449341
B11: 长期股权投资 | C11: 441494759 | D11: 181538429 | E11: 250040313 | F11: 228823950 | G11: 206748905 | H11: 199805151 | I11: 205738050 | J11: 95519959 | K11: 101536425 | L11: 46449341
B12: 其他权益工具投资 | C12: 82682735 | D12: 91054345 | E12: 77566743 | F12: 69320755 | G12: 58000000
A13: 经营资产 | C13: =SUM(C14:C24) -> 16094542311 | D13: =SUM(D14:D24) -> 14147469320 | E13: =SUM(E14:E24) -> 12235113740 | F13: =SUM(F14:F24) -> 10129858419 | G13: =SUM(G14:G24) -> 8668361952 | H13: =SUM(H14:H24) -> 8471317618 | I13: =SUM(I14:I24) -> 9033666442 | J13: =SUM(J14:J24) -> 8680763546 | ... L13: =SUM(L14:L24) -> 6631629264
B14: 存货 | C14: 5970614068 | D14: 5143615319 | E14: 5403360356 | F14: 4327048485 | G14: 3280989599 | H14: 3280465303 | I14: 3241739977 | J14: 2974677451 | K14: 2785865099 | L14: =2494920809+320467619 -> 2815388428
B15: 应收票据 | C15: 812397864 | D15: 367992386 | E15: 204452983 | F15: 38888270 | G15: 19430381 | H15: 20011631 | I15: 710399926 | J15: 921383461 | K15: 871597857 | L15: 569748367
B16: 应收账款 | C16: 8157067130 | D16: 7128016386 | E16: 5257513588 | F16: 4311233501 | G16: 3734495117 | H16: 3457428686 | I16: 3593707590 | J16: 3716260518 | K16: 3636343106 | L16: 2762405078
B17: 预付款项 | C17: 305455256 | D17: 316529520 | E17: 235934604 | F17: 238959820 | G17: 173525313 | H17: 222501827 | I17: 220126772 | J17: 195521295 | K17: 150956724 | L17: 178812459
B18: 其他应收款 | C18: 126106574 | D18: 143819252 | E18: 138098796 | F18: 160746854 | G18: 526506578 | H18: 472000751 | I18: 510753825 | J18: 105412820 | K18: 118430342 | L18: 86561210
B19: 其他流动资产 | C19: 317730736 | D19: 281151242 | E19: 273366871 | F19: 158536366 | G19: 252804600 | H19: 320404434 | I19: 313634314 | J19: 259548554 | K19: 174699089
B20: 其他非流动资产 | I20: 842960 | J20: 1210710 | K20: 289450
B21: 一年到期流动资产 | D21: 316416243 | I21: 190000000
B22: 一年内到期非流动资产 | G22: 160000000 | K22: 16936288 | L22: 14065004
B23: 长期应收款 | C23: 30104757 | D23: 28891321 | E23: 316416243 | F23: 461516243 | H23: 180000000 | J23: 190000000
B24: 递延所得税资产 | C24: 375065926 | D24: 421037651 | E24: 405970299 | F24: 432928880 | G24: 520610364 | H24: 518504986 | I24: 252461078 | J24: 316748737 | K24: 193403942 | L24: 204648718
A25: 长期资产 | C25: =SUM(C26:C31) -> 25921750571 | D25: =SUM(D26:D31) -> 22371514457 | E25: =SUM(E26:E31) -> 20039597823 | F25: =SUM(F26:F31) -> 18909202022 | G25: =SUM(G26:G31) -> 19078628686 | H25: =SUM(H26:H31) -> 20153605835 | I25: =SUM(I26:I31) -> 18450256913 | J25: =SUM(J26:J31) -> 16310925095 | ... L25: =SUM(L26:L31) -> 12043995724
B26: 固定资产 | C26: 16449536181 | D26: 14955242773 | E26: 14445878801 | F26: 14501764063 | G26: 14260438910 | H26: 14520366436 | I26: 13629887296 | J26: 11332521554 | K26: 9267464872 | L26: 7688519842
B27: 在建工程 | C27: 6509671375 | D27: 4766144830 | E27: 3133499992 | F27: 1976816816 | G27: 2354298463 | H27: 2901032823 | I27: 2936812592 | J27: 3366783284 | K27: 3821964355 | L27: 2842566308
B28: 使用权资产 | C28: 532127082 | D28: 628448631 | E28: 575442101 | F28: 595392579 | G28: 607068550 | H28: 701329178
B29: 无形资产 | C29: 1600767546 | D29: 1315862480 | E29: 1245410813 | F29: 1235091876 | G29: 1270843245 | H29: 1337282523 | I29: 1219578721 | J29: 1098130404 | K29: 1148077027 | L29: 1179236213
B30: 商誉 | C30: 153707174 | D30: 154940513 | E30: 154940513 | F30: 154940513 | G30: 154940513 | H30: 154940513 | I30: 153707174 | J30: 74678326 | K30: 74678326 | L30: 74678326
B31: 长期待摊 | C31: 675941213 | D31: 550875230 | E31: 484425603 | F31: 445196175 | G31: 431039005 | H31: 538654362 | I31: 510271130 | J31: 438811527 | K31: 290472267 | L31: 258995035
A33: 负债 | C33: =C35+C49 -> 27568613358 | D33: =D35+D49 -> 25219085168 | E33: =E35+E49 -> 21779200663 | F33: =F35+F49 -> 18490789663 | G33: =G35+G49 -> 16832717886 | H33: =H35+H49 -> 17457198085 | I33: =I35+I49 -> 14300566064 | J33: =J35+J49 -> 13123026239 | ... L33: =L35+L49 -> 8411904960
A35: 经营负债 | C35: =SUM(C36:C48) -> 12573314784 | D35: =SUM(D36:D48) -> 10683161206 | E35: =SUM(E36:E48) -> 8767191100 | F35: =SUM(F36:F48) -> 7285142620 | G35: =SUM(G36:G48) -> 6398132763 | H35: =SUM(H36:H48) -> 6073728547 | I35: =SUM(I36:I48) -> 5897287132 | J35: =SUM(J36:J48) -> 5202569264 | ... L35: =SUM(L36:L48) -> 3669285297
B36: 应付票据 | C36: 3007490592 | D36: 2825386573 | E36: 2128399828 | F36: 1623267716 | G36: 1166210433 | H36: 860739543 | K36: 613982362 | L36: 460160232
B37: 应付账款 | C37: 2795604397 | D37: 2697600166 | E37: 2025309794 | F37: 1524955089 | G37: 1299794957 | H37: 1236580062 | I37: 2465349981 | J37: 2401097118 | K37: 1300220344 | L37: 909111745
B38: 预收款项 | K38: 21435585 | L38: 33985494
B39: 合同负债 | C39: 807312590 | D39: 979067305 | E39: 931585408 | F39: 863737090 | G39: 756282114 | H39: 695400166 | I39: 594503112 | J39: 442282880
B40: 应付职工薪酬 | C40: 972229163 | D40: 816372688 | E40: 660389674 | F40: 530495062 | G40: 489357281 | H40: 473972041 | I40: 483015711 | J40: 439505286 | K40: 420291759 | L40: 353759783
B41: 应交税费 | C41: 600754415 | D41: 546430527 | E41: 404719169 | F41: 319532528 | G41: 302321505 | H41: 344357096 | I41: 449716675 | J41: 313192643 | K41: 558062870 | L41: 335339211
B42: 其他应付款 | C42: 2226134441 | D42: 1622250140 | E42: 1681942320 | F42: 1496548775 | G42: 1376997551 | H42: 1555660964 | I42: 1208118598 | J42: 1069106178 | K42: 1090612474 | L42: =1087807096+9551912 -> 1097359008
B43: 其他流动负债 | C43: 140768878
B44: 递延收益 | C44: 819351754 | D44: 725121670 | E44: 671049135 | F44: 677682302 | G44: 735789390 | H44: 673448373 | I44: 536834206 | J44: 461594918 | K44: 481827522 | L44: 386986443
B45: 长期应付款 | C45: 53855052 | D45: 59287444 | E45: 64473498 | F45: 69424385 | G45: 75694702 | H45: 72490512
B46: 预计负债 | C46: 34486563
B47: 其他非流动负债 | C47: 410555755
B48: 递延所得税负债 | C48: 704771184 | D48: 411644693 | E48: 199322274 | F48: 179499673 | G48: 195684830 | H48: 161079790 | I48: 159748849 | J48: 75790241 | K48: 80407573 | L48: 92583381
A49: 有息负债 | C49: =SUM(C50:C57) -> 14995298574 | D49: =SUM(D50:D57) -> 14535923962 | E49: =SUM(E50:E57) -> 13012009563 | F49: =SUM(F50:F57) -> 11205647043 | G49: =SUM(G50:G57) -> 10434585123 | H49: =SUM(H50:H57) -> 11383469538 | I49: =SUM(I50:I57) -> 8403278932 | J49: =SUM(J50:J57) -> 7920456975 | ... L49: =SUM(L50:L57) -> 4742619663
B50: 短期借款 | C50: 4588583967 | D50: 5413589161 | E50: 6076527372 | F50: 5925550792 | G50: 6165804499 | H50: 8491599785 | I50: 5548826223 | J50: 5379161092 | K50: 4255037518 | L50: 2636462068
B51: 长期借款 | C51: 7212920000 | D51: 8513100000 | E51: 3007000000 | F51: 1138940000 | G51: 1985000000 | H51: 1193000000 | I51: 1246875075 | J51: 1711000000 | K51: 776000000 | L51: 848000000
B52: 衍生金融资产负债 | G52: 795244 | H52: 3795000 | I52: 3077741 | J52: 23190469 | L52: 925435
B53: 应付债券 | F53: 1198778297 | G53: 1198784928 | J53: 798605414 | K53: 797530999
B54: 应计利息 | K54: 15286048 | L54: 22642760
B55: 其他流动负债 | E55: 1306346479 | F55: 806775458 | G55: 303131507 | I55: 300984971 | K55: 608604575
B56: 一年内到期的非流动负债 | C56: 2850055339 | D56: 202102553 | E56: 2145153663 | F56: 1627919125 | G56: 270557753 | H56: 1123793163 | I56: 1303514922 | J56: 8500000 | K56: 808000000 | L56: 1234589400
B57: 租赁负债 | C57: 343739268 | D57: 407132248 | E57: 476982049 | F57: 507683371 | G57: 510511192 | H57: 571281590
A60: 所有者权益 | C60: =SUM(C61:C67) -> 35685569178 | D60: =SUM(D61:D67) -> 31411322327 | E60: =SUM(E61:E67) -> 28988298128 | F60: =SUM(F61:F67) -> 26294104291 | G60: =SUM(G61:G67) -> 21590907298 | H60: =SUM(H61:H67) -> 21369081522 | I60: =SUM(I61:I67) -> 20189872606 | J60: =SUM(J61:J67) -> 18797871807 | ... L60: =SUM(L61:L67) -> 16415066432
B61: 实收资本（或股本） | C61: 2609743532 | D61: 2609743532 | E61: 2609743532 | F61: 2609743532 | G61: 2508617532 | H61: 2508617532 | I61: 2508617532 | J61: 2508617532 | K61: 2508617532 | L61: 2508617532
B62: 资本公积 | C62: 9700750924 | D62: 9700750924 | E62: 9700750924 | F62: 9700750924 | G62: 6222912435 | H62: 6223078157 | I62: 6223078157 | J62: 6224133097 | K62: 6228753097 | L62: 6228932452
B63: 减：库存股
B64: 其他综合收益 | C64: 339806293 | D64: 176931220 | E64: 120835879 | F64: -430305845 | G64: -373980332 | H64: 121015957 | I64: -41473936 | J64: -204408762 | K64: 91038123 | L64: -271367181
B65: 盈余公积 | C65: 4418068403 | D65: 3931592517 | E65: 3581885299 | F65: 3180340261 | G65: 2931419311 | H65: 2688959735 | I65: 2350361581 | J65: 1912821638 | K65: 1634319463 | L65: 1343078789
B66: 未分配利润 | C66: 18625997091 | D66: 15007163446 | E66: 12989794025 | F66: 11245487054 | G66: 10305548562 | H66: 9828694828 | I66: 9150322858 | J66: 8352285561 | K66: 7570889309 | L66: 6599365793
B67: 少数股东权益 | C67: -8797065 | D67: -14859312 | E67: -14711531 | F67: -11911635 | G67: -3610210 | H67: -1284687 | I67: -1033586 | J67: 4422741 | K67: 4928270 | L67: 6439047
C69: =C60+C33 -> 63254182536 | D69: =D60+D33 -> 56630407495 | E69: =E60+E33 -> 50767498791 | F69: =F60+F33 -> 44784893954 | G69: =G60+G33 -> 38423625184 | H69: =H60+H33 -> 38826279607 | I69: =I60+I33 -> 34490438670 | J69: =J60+J33 -> 31920898046 | ... L69: =L60+L33 -> 24826971392
B71: 分红 | C71: 4.6975384e+09 | D71: 3.3926666e+09 | E71: 3262179415 | F71: 2609743532 | G71: 1957307649 | H71: 1881463149 | I71: 2884910162 | J71: 1881463149 | K71: 1881463149 | L71: 1881463149

Sheet 损益现金流
B1: 2024 | C1: 2023 | D1: 2022 | E1: 2021 | F1: 2020 | G1: 2019 | H1: 2018 | I1: 2017 | J1: 2016 | K1: 2015
A2: 营收 | B2: 39251657267 | C2: 33160996641 | D2: 28098754166 | E2: 23603063361 | F2: 19906593468 | G2: 21103877523 | H2: 20224985720 | I2: 18713034974 | J2: 16621336273 | K2: 13573495055
A3: 成本 | B3: 25030877441 | C3: 21424326140 | D3: 18535445134 | E3: 15129053236 | F3: 12042217543 | G3: 13197554393 | H3: 11603054947 | I3: 10712611816 | J3: 9463313931 | K3: 7814343237
A4: 毛利率 | B4: =1-B3/B2 -> 0.36229756 | C4: =1-C3/C2 -> 0.35392997 | D4: =1-D3/D2 -> 0.34034637 | E4: =1-E3/E2 -> 0.35902162 | F4: =1-F3/F2 -> 0.39506387 | G4: =1-G3/G2 -> 0.37463841 | H4: =1-H3/H2 -> 0.42630096 | I4: =1-I3/I2 -> 0.4275321 | ... K4: =1-K3/K2 -> 0.42429395
A5: 税金及附加 | B5: 285987048 | C5: 239896621 | D5: 225341476 | E5: 204629142 | F5: 198182840 | G5: 197816747 | H5: 203072222 | I5: 200263617 | J5: 174265074 | K5: 112453855
A6: 销售费用 | B6: 1180260909 | C6: 1538783486 | D6: 1350721298 | E6: 1150992397 | F6: 1474366072 | G6: 1481567161 | H6: 1467671276 | I6: 1274308845 | J6: 1184740033 | K6: 1020584621
A7: 管理费用 | B7: 2888289768 | C7: 2486049334 | D7: 2142932036 | E7: 1944179027 | F7: 2076624937 | G7: 2185363063 | H7: 2063072209 | I7: 1797379424 | J7: 2392097806 | K7: 1873364984
A8: 研发费用 | B8: 1677751298 | C8: 1403030121 | D8: 1248592812 | E8: 997203019 | F8: 815579258 | G8: 813129835 | H8: 887721987 | I8: 803441192
A10: 其他收益 | B10: 400415185 | C10: 262917177 | D10: 215071387 | E10: 242337506 | F10: 352820556 | G10: 181754102 | H10: 146750220 | I10: 190690589
A11: 信用减值 | B11: -3562889 | C11: -17109861 | D11: -4092781 | E11: -5436372 | F11: -5986645 | G11: -20511657 | H11: -28131575
A12: 资产减值 | B12: =-108088278 -> -108088278 | C12: -205314035 | D12: -140304975 | E12: -18976018 | F12: -30973964 | G12: -3939955 | H12: -22335530 | I12: -5110700 | J12: -11224597 | K12: -11540935
A13: 资产处置 | B13: 13102488 | C13: 1647225 | D13: -6083766 | E13: 484341 | F13: 75117728 | G13: 4347754 | H13: -1279203 | I13: -26217990
A15: 营业外收入 | B15: 35905331 | C15: 49843149 | D15: 80855034 | E15: 217974835 | F15: 57628048 | G15: 109494454 | H15: 60687441 | I15: 27172108 | J15: 115204091 | K15: 129935252
A16: 营业外成本 | B16: 120136061 | C16: 125106357 | D16: 163122132 | E16: 161162665 | F16: 214664627 | G16: 294294341 | H16: 71545321 | I16: 17376997 | J16: 35438675 | K16: 138450464
A18: 息税前经营利润 | B18: =B2-B3-SUM(B5:B8)+SUM(B10:B13)+B15-B16 -> 8406126579 | C18: =C2-C3-SUM(C5:C8)+SUM(C10:C13)+C15-C16 -> 6035788237 | D18: =D2-D3-SUM(D5:D8)+SUM(D10:D13)+D15-D16 -> 4578044177 | E18: =E2-E3-SUM(E5:E8)+SUM(E10:E13)+E15-E16 -> 4452228167 | F18: =F2-F3-SUM(F5:F8)+SUM(F10:F13)+F15-F16 -> 3533563914 | G18: =G2-G3-SUM(G5:G8)+SUM(G10:G13)+G15-G16 -> 3205296681 | H18: =H2-H3-SUM(H5:H8)+SUM(H10:H13)+H15-H16 -> 4084539111 | I18: =I2-I3-SUM(I5:I8)+SUM(I10:I13)+I15-I16 -> 4094187090 | ... K18: =K2-K3-SUM(K5:K8)+SUM(K10:K13)+K15-K16 -> 2732692211
A20: 金融资产收益 | B20: =SUM(B21:B23) -> 924966003 | C20: =SUM(C21:C23) -> 602544066 | D20: =SUM(D21:D23) -> 231495735 | E20: =SUM(E21:E23) -> 195413923 | F20: =SUM(F21:F23) -> 348762592 | G20: =SUM(G21:G23) -> 336984661 | H20: =SUM(H21:H23) -> 335452093 | I20: =SUM(I21:I23) -> 137540567 | ... K20: =SUM(K21:K23) -> 16915996
A21: 投资收益 | B21: =-11293376+-44874617 -> -56167993 | C21: -9802782 | D21: =-16364000+-12840733 -> -29204733 | E21: =5235616+45414980+-14677491 -> 35973105 | F21: =68910527+-9922937+165722 -> 59153312 | G21: =98833082-10431971-90255 -> 88310856 | H21: =35253973+270490 -> 35524463
A22: 利息收入 | B22: 979192040 | C22: 614002388 | D22: 262733645 | E22: 168837719 | F22: 290289764 | G22: 284421399 | H22: 236034167 | I22: 156658899 | J22: 106577485 | K22: 19724867
A23: 公允价值变动 | B23: 1941956 | C23: =-1655540 -> -1655540 | D23: -2033177 | E23: -9396901 | F23: -680484 | G23: -35747594 | H23: 63893463 | I23: -19118332 | J23: 2776702 | K23: -2808871
A25: 长期投资收益 | B25: =SUM(B26:B28) -> -15801862 | C25: =SUM(C26:C28) -> 4290148 | D25: =SUM(D26:D28) -> 20962737 | E25: =SUM(E26:E28) -> 26975045 | F25: =SUM(F26:F28) -> 11843754 | G25: =SUM(G26:G28) -> -5932899 | H25: =SUM(H26:H28) -> 667776495 | I25: =SUM(I26:I28) -> 23390958 | ... K25: =SUM(K26:K28) -> 23781843
A26: 长期股权投资收益 | B26: =-15801862 -> -15801862 | C26: =10797721+-6507573 -> 4290148 | D26: 20962737 | E26: 26975045 | F26: 11843754 | G26: -5932899 | H26: =3743957+664032538 -> 667776495 | I26: =-6016466+29407424 -> 23390958 | J26: 41956332 | K26: 23781843
A27: 其他权益工具投资
A28: 公允价值变动
A30: 息税前净利润 | B30: =B18+B20+B25 -> 9315290720 | C30: =C18+C20+C25 -> 6642622451 | D30: =D18+D20+D25 -> 4830502649 | E30: =E18+E20+E25 -> 4674617135 | F30: =F18+F20+F25 -> 3894170260 | G30: =G18+G20+G25 -> 3536348443 | H30: =H18+H20+H25 -> 5087767699 | I30: =I18+I20+I25 -> 4255118615 | ... K30: =K18+K20+K25 -> 2773390050
A31: 利息支出 | B31: 288507082 | C31: 288319603 | D31: =284355835+14674435+-10908011 -> 288122259 | E31: =312535638+12662034-6256881 -> 318940791 | F31: =353836981+13932104-13016682 -> 354752403 | G31: =447223558+13912513-28456551 -> 432679520 | H31: =376230473 -> 376230473 | I31: =182373020 -> 182373020 | J31: =157713120 -> 157713120 | K31: =190512029 -> 190512029
A32: 财务费用 | B32: =24284937+11679111 -> 35964048 | C32: =-368696286+6977220 -> -361719066 | D32: =-1045237867+8512570 -> -1036725297 | E32: =528006272+8827978 -> 536834250 | F32: =422467723+7355091 -> 429822814 | G32: =-135763953+8294824 -> -127469129 | H32: =+-258516410+7693358 -> -250823052 | I32: =387506549+5517279 -> 393023828 | J32: =+-458716176+8148119 -> -450568057 | K32: =+-466734319+6887612 -> -459846707
A33: 所得税 | B33: 1486781220 | C33: 1086913641 | D33: 826310042 | E33: 675861301 | F33: 511144107 | G33: 332955880 | H33: 855187629 | I33: 531479253 | J33: 776909142 | K33: 435226131
A35: 净利润 | B35: =B30-B32-B33-B31 -> 7504038370 | C35: =C30-C32-C33-C31 -> 5629108273 | D35: =D30-D32-D33-D31 -> 4752795645 | E35: =E30-E32-E33-E31 -> 3142980793 | F35: =F30-F32-F33-F31 -> 2598450936 | G35: =G30-G32-G33-G31 -> 2898182172 | H35: =H30-H32-H33-H31 -> 4107172649 | I35: =I30-I32-I33-I31 -> 3148242514 | ... K35: =K30-K32-K33-K31 -> 2607498597
A36: 资产减值准备 | B36: 108088278 | C36: 205314035 | D36: 140304975 | E36: 18976018 | F36: 30973964 | G36: 3939955 | H36: 50467105 | I36: 5124005 | J36: 11224597 | K36: 11540935
A37: 信用减值损失 | B37: 3562889 | C37: 17109861 | D37: 4092781 | E37: 5436372 | F37: 5986645 | G37: 20511657
A38: 固定资产折旧、油气资产折耗、生产性生物资产折旧 | B38: 2133735188 | C38: 2006016143 | D38: 1895051137 | E38: 1816292295 | F38: 1796451028 | G38: 1658464142 | H38: 1397193868 | I38: 1170550643 | J38: 1064314933 | K38: 876235955
A39: 使用权资产摊销 | B39: 168226551 | C39: 141396351 | D39: 122698462 | E39: 123037830 | F39: 118490311 | G39: 107566459
A40: 无形资产摊销 | B40: 90344881 | C40: 75882503 | D40: 68021416 | E40: 70365542 | F40: 72520085 | G40: 75727709 | H40: 50146297 | I40: 44348345 | J40: 42668547 | K40: 36109422
A41: 长期待摊费用摊销 | B41: 335192027 | C41: 299148362 | D41: 259296442 | E41: 241956999 | F41: 254543544 | G41: 288399999 | H41: 239827437 | I41: 183493510 | J41: 147684382 | K41: 119555034
A42: 处置固定资产、无形资产和其他长期资产的损失 | B42: 92206108 | C42: 100067948 | D42: 127946902 | E42: 103003542 | F42: 67154040 | G42: 9278127 | H42: 63298310 | I42: 26217990 | J42: 17315990 | K42: 65685144
A43: 固定资产报废损失
A44: 公允价值变动损失 | B44: -1941956 | C44: 1655540 | D44: 2033177 | E44: 9396901 | F44: 680484 | G44: 35747594 | H44: -63893463 | I44: 19118332 | J44: -2776702 | K44: 2808871
A45: 财务费用（收益以“－”号填列） | B45: -127999869 | C45: -156817467 | D45: -623268615 | E45: 567719920 | F45: 731090764 | G45: 323747885 | H45: 122942899 | I45: 496898960 | J45: -249338912 | K45: -109367084
A46: 投资损失（收益以“－”号填列） | B46: 60676479 | C46: 863478 | D46: -4598737 | E46: -77625641 | F46: -80920003 | G46: -92809928 | H46: -703300958 | I46: -23390958 | J46: -41956332 | K46: -23781843
A47: 递延所得税资产减少 | B47: 45971725 | C47: -15067352 | D47: 26958581 | E47: 87681484 | F47: -2105378 | G47: -266043908 | H47: 64287659 | I47: -87191702 | J47: 11244776 | K47: -14837203
A48: 递延所得税负债增加 | B48: 295219393 | C48: 208950519 | D48: 17761104 | E48: -16185157 | F48: 34605040 | G48: 1330941 | H48: 66551272 | I48: -4617332 | J48: -12175808 | K48: 18828115
A49: 存货的减少 | B49: -915925306 | C49: 230609935 | D49: -1107600709 | E49: -1065034904 | F49: -31498260 | G49: -42665281 | H49: -237853502 | I49: -187602869 | J49: -290003664 | K49: -302464655
A50: 经营性应收项目的减少 | B50: -2556960709 | C50: -2780290232 | D50: -1158638442 | E50: -261733125 | F50: -724250478 | G50: 6752325 | H50: 412571832 | I50: -149949345 | J50: -1142132470 | K50: -222012488
A51: 经营性应付项目的增加 | B51: 1423578216 | C51: 1751550813 | D51: 1454725820 | E51: 986313659 | F51: 478607327 | G51: 151297996 | H51: 269195361 | I51: 306814239 | J51: 959561040 | K51: -36919595
A52: 递延收益摊销 | B52: -95824936 | C52: -90917820 | D52: -84538284 | E52: -75572887 | F52: -73017910 | G52: -52513013 | H52: -30745463 | I52: -23894571 | J52: -21372079 | K52: -14406179
A53: 其他
A54: 经营活动产生的现金流量净额 | B54: =B35+SUM(B36:B53) -> 8562187329 | C54: =C35+SUM(C36:C53) -> 7624580890 | D54: =D35+SUM(D36:D53) -> 5893041655 | E54: =E35+SUM(E36:E53) -> 5677009641 | F54: =F35+SUM(F36:F53) -> 5277762139 | G54: =G35+SUM(G36:G53) -> 5126914831 | H54: =H35+SUM(H36:H53) -> 5807861303 | I54: =I35+SUM(I36:I53) -> 4924161761 | ... K54: =K35+SUM(K36:K53) -> 3014473026
A55: 销售商品、提供劳务收到的现金 | B55: 37770735435 | C55: 31482964361 | D55: 29140807061 | E55: 24732625116 | F55: 20384558374 | G55: 22628355978 | H55: 22728927626 | I55: 20482066535 | J55: 17281659057 | K55: 14742618341
A56: 收到的税费返还 | B56: 405196979 | C56: 327691192 | D56: 269276069 | E56: 303234772 | F56: 193527136 | G56: 240853074 | H56: 281901831 | I56: 274447357 | J56: 187711757 | K56: 193685258
A57: 收到其他与经营活动有关的现金 | B57: 1002006631 | C57: 753288481 | D57: 551237577 | E57: 588060384 | F57: 784161138 | G57: 674341156 | H57: 537292015 | I57: 467910670 | J57: 190245311 | K57: 112290050
A58: 经营活动现金流入小计 | B58: =SUM(B55:B57) -> 39177939045 | C58: =SUM(C55:C57) -> 32563944034 | D58: =SUM(D55:D57) -> 29961320707 | E58: =SUM(E55:E57) -> 25623920272 | F58: =SUM(F55:F57) -> 21362246648 | G58: =SUM(G55:G57) -> 23543550208 | H58: =SUM(H55:H57) -> 23548121472 | I58: =SUM(I55:I57) -> 21224424562 | ... K58: =SUM(K55:K57) -> 15048593649
A59: 购买商品、接受劳务支付的现金 | B59: 20211197125 | C59: 16335379211 | D59: 16462825366 | E59: 13312665463 | F59: 9870163235 | G59: 11860432727 | H59: 11999820697 | I59: 10795682357 | J59: 9259037288 | K59: 8501814057
A60: 支付给职工及为职工支付的现金 | B60: 7010421644 | C60: 5990441810 | D60: 5094796381 | E60: 4456225249 | F60: 4008966085 | G60: 4472992794 | H60: 3835696147 | I60: 3373546340 | J60: 2870928129 | K60: 1977131002
A61: 支付的各项税费 | B61: 3102334418 | C61: 2330286716 | D61: 2226889431 | E61: 1924319716 | F61: 1684037475 | G61: 1803160720 | H61: 1664451977 | I61: 1942764215 | J61: 1712607612 | K61: 1380505513
A62: 支付其他与经营活动有关的现金 | B62: 291798529 | C62: 283255407 | D62: 283767874 | E62: 253700203 | F62: 521317714 | G62: 280049136 | H62: 240291348 | I62: 188269889 | J62: 180068236 | K62: 174670051
A63: 经营活动现金流出小计 | B63: =SUM(B59:B62) -> 30615751716 | C63: =SUM(C59:C62) -> 24939363144 | D63: =SUM(D59:D62) -> 24068279052 | E63: =SUM(E59:E62) -> 19946910631 | F63: =SUM(F59:F62) -> 16084484509 | G63: =SUM(G59:G62) -> 18416635377 | H63: =SUM(H59:H62) -> 17740260169 | I63: =SUM(I59:I62) -> 16300262801 | ... K63: =SUM(K59:K62) -> 12034120623
A64: 经营活动产生的现金流量净额 | B64: =B58-B63 -> 8562187329 | C64: =C58-C63 -> 7624580890 | D64: =D58-D63 -> 5893041655 | E64: =E58-E63 -> 5677009641 | F64: =F58-F63 -> 5277762139 | G64: =G58-G63 -> 5126914831 | H64: =H58-H63 -> 5807861303 | I64: =I58-I63 -> 4924161761 | ... K64: =K58-K63 -> 3014473026
A66: 收回投资收到的现金 | C66: 30000000 | D66: 145100000
A67: 取得投资收益收到的现金 | D67: 4900000 | E67: 4900000 | F67: 4900000 | H67: 7350000 | J67: 9800000 | K67: 85583855
A68: 处置长期资产收回的现金净额 | B68: 102113490 | C68: 92261308 | D68: 83421411 | E68: 137828363 | F68: 33268980 | G68: 40775890 | H68: 63761705 | I68: 83503836 | J68: 55055543 | K68: 50230621
A69: 处置子公司收到的现金净额 | H69: 682452213 | I69: 148151006 | J69: 212515871 | K69: 52792397
A70: 收到其他与投资活动有关的现金 | B70: 15115931515 | C70: 7114797183 | E70: 334425941 | F70: 3675753634 | G70: 3933742827 | H70: 2065524464 | I70: 306805478 | J70: 316958240 | K70: 51425560
A71: 投资活动现金流入小计 | B71: =SUM(B66:B70) -> 15218045005 | C71: =SUM(C66:C70) -> 7237058491 | D71: =SUM(D66:D70) -> 233421411 | E71: =SUM(E66:E70) -> 477154304 | F71: =SUM(F66:F70) -> 3713922614 | G71: =SUM(G66:G70) -> 3974518717 | H71: =SUM(H66:H70) -> 2819088382 | I71: =SUM(I66:I70) -> 538460320 | ... K71: =SUM(K66:K70) -> 240032433
A72: 购建长期资产支付的现金 | B72: 5480872166 | C72: 4474711099 | D72: 3130253387 | E72: 2328511864 | F72: 1772542963 | G72: 2779502262 | H72: 3591741242 | I72: 3589995076 | J72: 3567561244 | K72: 3255541569
A73: 投资支付的现金 | C73: 20000000 | E73: 11320755 | F73: 58000000
A74: 取得子公司支付的现金净额 | G74: 20314292 | H74: 240131373
A75: 支付其他与投资活动有关的现金 | B75: 9681441916 | C75: 7191279706 | D75: 4759177210 | F75: 3050000000 | G75: 4300000000 | H75: 2315000000 | I75: 590000000 | J75: 200000000
A76: 投资活动现金流出小计 | B76: =SUM(B72:B75) -> 15162314082 | C76: =SUM(C72:C75) -> 11685990805 | D76: =SUM(D72:D75) -> 7889430597 | E76: =SUM(E72:E75) -> 2339832619 | F76: =SUM(F72:F75) -> 4880542963 | G76: =SUM(G72:G75) -> 7099816554 | H76: =SUM(H72:H75) -> 6146872615 | I76: =SUM(I72:I75) -> 4179995076 | ... K76: =SUM(K72:K75) -> 3255541569
A77: 投资活动产生的现金流量净额 | B77: =B71-B76 -> 55730923 | C77: =C71-C76 -> -4448932314 | D77: =D71-D76 -> -7656009186 | E77: =E71-E76 -> -1862678315 | F77: =F71-F76 -> -1166620349 | G77: =G71-G76 -> -3125297837 | H77: =H71-H76 -> -3327784233 | I77: =I71-I76 -> -3641534756 | ... K77: =K71-K76 -> -3015509136
A79: 吸收投资收到的现金 | E79: 3578964489 | K79: 6523837454
A80: 取得借款收到的现金 | B80: 12733066013 | C80: 17508736010 | D80: 11576879866 | E80: 8944555505 | F80: 13669218052 | G80: 15219223239 | H80: 13264898468 | I80: 10648891109 | J80: 8073542158 | K80: 7366909838
A81: 发行债券收到的现金 | J81: 800000000
A82: 收到其他与筹资活动有关的现金 | B82: 300000000 | D82: 3293000000 | E82: 1800000000 | F82: 3000000000 | G82: 1700000000 | H82: 300000000 | J82: 1200000000 | K82: 170900000
A83: 筹资活动现金流入小计 | B83: =SUM(B79:B82) -> 13033066013 | C83: =SUM(C79:C82) -> 17508736010 | D83: =SUM(D79:D82) -> 14869879866 | E83: =SUM(E79:E82) -> 14323519994 | F83: =SUM(F79:F82) -> 16669218052 | G83: =SUM(G79:G82) -> 16919223239 | H83: =SUM(H79:H82) -> 13564898468 | I83: =SUM(I79:I82) -> 10648891109 | ... K83: =SUM(K79:K82) -> 14061647292
A84: 偿还债务支付的现金 | B84: 12490915237 | C84: 15885156748 | D84: 13043226475 | E84: 9976147237 | F84: 17571509456 | G84: 14637412694 | H84: 13341532550 | I84: 9989267535 | J84: 7553966708 | K84: 7236350677
A85: 分配股利、利润或偿付利息支付的现金 | B85: 3713615661 | C85: 3596607894 | D85: 2907622437 | E85: 2277802231 | F85: 2219213537 | G85: 2310071663 | H85: 3303070399 | I85: 2110837864 | J85: 2035111204 | K85: 1714508880
A86: 支付其他与筹资活动有关的现金 | B86: 186709479 | C86: 307315590 | D86: 154914903 | E86: 117752796 | F86: 158014790 | G86: 87275186 | H86: 299581 | I86: 4620000 | J86: 59975603 | K86: 2722543
A87: 筹资活动现金流出小计 | B87: =SUM(B84:B86) -> 16391240377 | C87: =SUM(C84:C86) -> 19789080232 | D87: =SUM(D84:D86) -> 16105763815 | E87: =SUM(E84:E86) -> 12371702264 | F87: =SUM(F84:F86) -> 19948737783 | G87: =SUM(G84:G86) -> 17034759543 | H87: =SUM(H84:H86) -> 16644902530 | I87: =SUM(I84:I86) -> 12104725399 | ... K87: =SUM(K84:K86) -> 8953582100
A88: 筹资活动产生的现金流量净额 | B88: =B83-B87 -> -3358174364 | C88: =C83-C87 -> -2280344222 | D88: =D83-D87 -> -1235883949 | E88: =E83-E87 -> 1951817730 | F88: =F83-F87 -> -3279519731 | G88: =G83-G87 -> -115536304 | H88: =H83-H87 -> -3080004062 | I88: =I83-I87 -> -1455834290 | J88: =J83-J87 -> 424488643 | K88: =K84-K87 -> -1717231423

Sheet 收入成本
B1: 2024 | C1: 2023 | D1: 2022 | E1: 2021 | F1: 2020 | G1: 2019 | H1: 2018 | I1: 2017 | J1: 2016 | K1: 2015
A2: 主营业务
A3: 收入 | B3: 38710428679 | C3: 32650176898 | D3: 27650978801 | E3: 23261134069 | F3: 19641289272 | G3: 20765088255 | H3: 19883838974 | I3: 18190913985 | J3: 16290566904 | K3: 13272702952
A4: 汽车玻璃 | B4: 35711992929 | C4: 29887354294 | D4: 25591272963 | E4: 21379623201 | F4: 17942033181 | G4: 18957337043 | H4: 19351888769 | I4: 17868123103
A5: 浮法玻璃 | B5: 5960560140 | C5: 5708192224 | D5: 4536714592 | E5: 4029400372 | F5: 3491541713 | G5: 3644797566 | H5: 3220524367 | I5: 2899053827
A6: 其他
A8: 成本 | B8: 24922427939 | C8: 21310091980 | D8: 18410110199 | E8: 15039848812 | F8: 11944882127 | G8: 13060926884 | H8: 11488667084 | I8: 10484369082 | J8: 9329573724 | K8: 7696406162
A9: 汽车玻璃 | B9: 24943534919 | C9: 20745955716 | D9: 18002483558 | E9: 14952938108 | F9: 11757642229 | G9: 12411825241 | H9: 12407230011 | I9: 11274474151
A10: 浮法玻璃 | B10: 3812209771 | C10: 4069450484 | D10: 3329138613 | E10: 2571070680 | F10: 2150493545 | G10: 2372599956 | H10: 1870957442 | I10: 1841648761
A12: 毛利 | B12: =B3-B8 -> 13788000740 | C12: =C3-C8 -> 11340084918 | D12: =D3-D8 -> 9240868602 | E12: =E3-E8 -> 8221285257 | F12: =F3-F8 -> 7696407145 | G12: =G3-G8 -> 7704161371 | H12: =H3-H8 -> 8395171890 | I12: =I3-I8 -> 7706544903 | ... K12: =K3-K8 -> 5576296790
A13: 汽车玻璃 | B13: =B4-B9 -> 10768458010 | C13: =C4-C9 -> 9141398578 | D13: =D4-D9 -> 7588789405 | E13: =E4-E9 -> 6426685093 | F13: =F4-F9 -> 6184390952 | G13: =G4-G9 -> 6545511802 | H13: =H4-H9 -> 6944658758 | I13: =I4-I9 -> 6593648952 | ... K13: =K4-K9 -> 0
A14: 浮法玻璃 | B14: =B5-B10 -> 2148350369 | C14: =C5-C10 -> 1638741740 | D14: =D5-D10 -> 1207575979 | E14: =E5-E10 -> 1458329692 | F14: =F5-F10 -> 1341048168 | G14: =G5-G10 -> 1272197610 | H14: =H5-H10 -> 1349566925 | I14: =I5-I10 -> 1057405066 | ... K14: =K5-K10 -> 0
A16: 其他业务
A17: 收入 | B17: 541228588 | C17: 510819743 | D17: 447775365 | E17: 341929292 | F17: 265304196 | G17: 338789268 | H17: 341146746 | I17: 522120989 | J17: 330769369 | K17: 300792103
A18: 成本 | B18: 108449502 | C18: 114234160 | D18: 125334935 | E18: 89204424 | F18: 97335416 | G18: 136627509 | H18: 114387863 | I18: 228242734 | J18: 133740207 | K18: 117937075
A19: 毛利 | B19: =B17-B18 -> 432779086 | C19: =C17-C18 -> 396585583 | D19: =D17-D18 -> 322440430 | E19: =E17-E18 -> 252724868 | F19: =F17-F18 -> 167968780 | G19: =G17-G18 -> 202161759 | H19: =H17-H18 -> 226758883 | I19: =I17-I18 -> 293878255 | ... K19: =K17-K18 -> 182855028
A22: YoY
A23: 收入 | B23: =B3/C3-1 -> 0.18561161 | C23: =C3/D3-1 -> 0.18079642 | D23: =D3/E3-1 -> 0.18872015 | E23: =E3/F3-1 -> 0.18429772 | F23: =F3/G3-1 -> -0.054119634 | G23: =G3/H3-1 -> 0.044319876 | H23: =H3/I3-1 -> 0.093064317 | I23: =I3/J3-1 -> 0.11665322 | J23: =J3/K3-1 -> 0.22737373
A24: 汽车玻璃 | B24: =B4/C4-1 -> 0.19488639 | C24: =C4/D4-1 -> 0.1678729 | D24: =D4/E4-1 -> 0.19699364 | E24: =E4/F4-1 -> 0.19159423 | F24: =F4/G4-1 -> -0.053557304 | G24: =G4/H4-1 -> -0.02038828 | H24: =H4/I4-1 -> 0.083039817 | I24: =I4/J4-1 -> #DIV/0! | J24: =J4/K4-1 -> #DIV/0!
A25: 浮法玻璃 | B25: =B5/C5-1 -> 0.044211531 | C25: =C5/D5-1 -> 0.25822158 | D25: =D5/E5-1 -> 0.12590316 | E25: =E5/F5-1 -> 0.15404618 | F25: =F5/G5-1 -> -0.042047837 | G25: =G5/H5-1 -> 0.13174041 | H25: =H5/I5-1 -> 0.11088809 | I25: =I5/J5-1 -> #DIV/0! | J25: =J5/K5-1 -> #DIV/0!
B27: =B3/I3 -> 2.128009
B28: =B4/I4 -> 1.9986427
B29: =B5/I5 -> 2.0560364

Sheet Beta_04
B1: 定价 | C1: 定价 | D1: 2024 | E1: 2023 | F1: 2022 | G1: 2021 | H1: 2020 | I1: 2019 | J1: 2018 | K1: 2017 | L1: 2016 | M1: 2015
A2: 资产 | D2: =balance!C2 -> 63254182536 | E2: =balance!D2 -> 56630407495 | F2: =balance!E2 -> 50767498791 | G2: =balance!F2 -> 44784893954 | H2: =balance!G2 -> 38423625184 | I2: =balance!H2 -> 38826279607 | J2: =balance!I2 -> 34490438670 | K2: =balance!J2 -> 31920898046 | ... M2: =balance!L2 -> 24640919497
A3: 现金 | D3: =balance!C4 -> 20713712160 | E3: =balance!D4 -> 19838830944 | F3: =balance!E4 -> 18165180172 | G3: =balance!F4 -> 15447688808 | H3: =balance!G4 -> 10411885641 | I3: =balance!H4 -> 10001551003 | J3: =balance!I4 -> 6800777265 | K3: =balance!J4 -> 6833689446 | ... M3: =balance!L4 -> 5918845168
A4: 投资 | D4: =balance!C10 -> 524177494 | E4: =balance!D10 -> 272592774 | F4: =balance!E10 -> 327607056 | G4: =balance!F10 -> 298144705 | H4: =balance!G10 -> 264748905 | I4: =balance!H10 -> 199805151 | J4: =balance!I10 -> 205738050 | K4: =balance!J10 -> 95519959 | ... M4: =balance!L10 -> 46449341
A5: 运营资产 | D5: =balance!C13 -> 16094542311 | E5: =balance!D13 -> 14147469320 | F5: =balance!E13 -> 12235113740 | G5: =balance!F13 -> 10129858419 | H5: =balance!G13 -> 8668361952 | I5: =balance!H13 -> 8471317618 | J5: =balance!I13 -> 9033666442 | K5: =balance!J13 -> 8680763546 | ... M5: =balance!L13 -> 6631629264
A6: 应收 | D6: =balance!C15+balance!C16 -> 8969464994 | E6: =balance!D15+balance!D16 -> 7496008772 | F6: =balance!E15+balance!E16 -> 5461966571 | G6: =balance!F15+balance!F16 -> 4350121771 | H6: =balance!G15+balance!G16 -> 3753925498 | I6: =balance!H15+balance!H16 -> 3477440317 | J6: =balance!I15+balance!I16 -> 4304107516 | K6: =balance!J15+balance!J16 -> 4637643979 | ... M6: =balance!L15+balance!L16 -> 3332153445
A7: 预付 | D7: =balance!C17 -> 305455256 | E7: =balance!D17 -> 316529520 | F7: =balance!E17 -> 235934604 | G7: =balance!F17 -> 238959820 | H7: =balance!G17 -> 173525313 | I7: =balance!H17 -> 222501827 | J7: =balance!I17 -> 220126772 | K7: =balance!J17 -> 195521295 | ... M7: =balance!L17 -> 178812459
A8: 存货 | D8: =balance!C14 -> 5970614068 | E8: =balance!D14 -> 5143615319 | F8: =balance!E14 -> 5403360356 | G8: =balance!F14 -> 4327048485 | H8: =balance!G14 -> 3280989599 | I8: =balance!H14 -> 3280465303 | J8: =balance!I14 -> 3241739977 | K8: =balance!J14 -> 2974677451 | ... M8: =balance!L14 -> 2815388428
A9: 长期资产 | D9: =balance!C25 -> 25921750571 | E9: =balance!D25 -> 22371514457 | F9: =balance!E25 -> 20039597823 | G9: =balance!F25 -> 18909202022 | H9: =balance!G25 -> 19078628686 | I9: =balance!H25 -> 20153605835 | J9: =balance!I25 -> 18450256913 | K9: =balance!J25 -> 16310925095 | ... M9: =balance!L25 -> 12043995724
A10: 负债 | D10: =balance!C33 -> 27568613358 | E10: =balance!D33 -> 25219085168 | F10: =balance!E33 -> 21779200663 | G10: =balance!F33 -> 18490789663 | H10: =balance!G33 -> 16832717886 | I10: =balance!H33 -> 17457198085 | J10: =balance!I33 -> 14300566064 | K10: =balance!J33 -> 13123026239 | ... M10: =balance!L33 -> 8411904960
A11: 预收 | D11: =balance!C39+balance!C38 -> 807312590 | E11: =balance!D39+balance!D38 -> 979067305 | F11: =balance!E39+balance!E38 -> 931585408 | G11: =balance!F39+balance!F38 -> 863737090 | H11: =balance!G39+balance!G38 -> 756282114 | I11: =balance!H39+balance!H38 -> 695400166 | J11: =balance!I39+balance!I38 -> 594503112 | K11: =balance!J39+balance!J38 -> 442282880 | ... M11: =balance!L39+balance!L38 -> 33985494
A12: 应付 | D12: =balance!C36+balance!C37 -> 5803094989 | E12: =balance!D36+balance!D37 -> 5522986739 | F12: =balance!E36+balance!E37 -> 4153709622 | G12: =balance!F36+balance!F37 -> 3148222805 | H12: =balance!G36+balance!G37 -> 2466005390 | I12: =balance!H36+balance!H37 -> 2097319605 | J12: =balance!I36+balance!I37 -> 2465349981 | K12: =balance!J36+balance!J37 -> 2401097118 | ... M12: =balance!L36+balance!L37 -> 1369271977
A13: 有息负债 | D13: =balance!C49 -> 14995298574 | E13: =balance!D49 -> 14535923962 | F13: =balance!E49 -> 13012009563 | G13: =balance!F49 -> 11205647043 | H13: =balance!G49 -> 10434585123 | I13: =balance!H49 -> 11383469538 | J13: =balance!I49 -> 8403278932 | K13: =balance!J49 -> 7920456975 | ... M13: =balance!L49 -> 4742619663
A14: 权益 | D14: =balance!C60 -> 35685569178 | E14: =balance!D60 -> 31411322327 | F14: =balance!E60 -> 28988298128 | G14: =balance!F60 -> 26294104291 | H14: =balance!G60 -> 21590907298 | I14: =balance!H60 -> 21369081522 | J14: =balance!I60 -> 20189872606 | K14: =balance!J60 -> 18797871807 | ... M14: =balance!L60 -> 16415066432
A15: 资本投入 | D15: =balance!C61+balance!C62 -> 12310494456 | E15: =balance!D61+balance!D62 -> 12310494456 | F15: =balance!E61+balance!E62 -> 12310494456 | G15: =balance!F61+balance!F62 -> 12310494456 | H15: =balance!G61+balance!G62 -> 8731529967 | I15: =balance!H61+balance!H62 -> 8731695689 | J15: =balance!I61+balance!I62 -> 8731695689 | K15: =balance!J61+balance!J62 -> 8732750629 | ... M15: =balance!L61+balance!L62 -> 8737549984
A16: 未分配利润 | D16: =balance!C66 -> 18625997091 | E16: =balance!D66 -> 15007163446 | F16: =balance!E66 -> 12989794025 | G16: =balance!F66 -> 11245487054 | H16: =balance!G66 -> 10305548562 | I16: =balance!H66 -> 9828694828 | J16: =balance!I66 -> 9150322858 | K16: =balance!J66 -> 8352285561 | ... M16: =balance!L66 -> 6599365793
A17: 股息分红 | D17: =balance!C71 -> 4.6975384e+09 | E17: =balance!D71 -> 3.3926666e+09 | F17: =balance!E71 -> 3262179415 | G17: =balance!F71 -> 2609743532 | H17: =balance!G71 -> 1957307649 | I17: =balance!H71 -> 1881463149 | J17: =balance!I71 -> 2884910162 | K17: =balance!J71 -> 1881463149 | ... M17: =balance!L71 -> 1881463149
A19: 现金结构 | D19: =D3 -> 20713712160 | E19: =E3 -> 19838830944 | F19: =F3 -> 18165180172 | G19: =G3 -> 15447688808 | H19: =H3 -> 10411885641 | I19: =I3 -> 10001551003 | J19: =J3 -> 6800777265 | K19: =K3 -> 6833689446 | ... M19: =M3 -> 5918845168
A20: 利润留存 | D20: =D16 -> 18625997091 | E20: =E16 -> 15007163446 | F20: =F16 -> 12989794025 | G20: =G16 -> 11245487054 | H20: =H16 -> 10305548562 | I20: =I16 -> 9828694828 | J20: =J16 -> 9150322858 | K20: =K16 -> 8352285561 | ... M20: =M16 -> 6599365793
A21: 股东、负债 | D21: =D19-D20 -> 2087715069 | E21: =E19-E20 -> 4831667498 | F21: =F19-F20 -> 5175386147 | G21: =G19-G20 -> 4202201754 | H21: =H19-H20 -> 106337079 | I21: =I19-I20 -> 172856175 | J21: =J19-J20 -> -2349545593 | K21: =K19-K20 -> -1518596115 | ... M21: =M19-M20 -> -680520625
A23: 折旧摊销 | D23: =SUM(损益现金流!B38:B41) -> 2727498647 | E23: =SUM(损益现金流!C38:C41) -> 2522443359 | F23: =SUM(损益现金流!D38:D41) -> 2345067457 | G23: =SUM(损益现金流!E38:E41) -> 2251652666 | H23: =SUM(损益现金流!F38:F41) -> 2242004968 | I23: =SUM(损益现金流!G38:G41) -> 2130158309 | J23: =SUM(损益现金流!H38:H41) -> 1687167602 | K23: =SUM(损益现金流!I38:I41) -> 1398392498 | ... M23: =SUM(损益现金流!K38:K41) -> 1031900411
A24: 资本开支 | D24: =损益现金流!B72 -> 5480872166 | E24: =损益现金流!C72 -> 4474711099 | F24: =损益现金流!D72 -> 3130253387 | G24: =损益现金流!E72 -> 2328511864 | H24: =损益现金流!F72 -> 1772542963 | I24: =损益现金流!G72 -> 2779502262 | J24: =损益现金流!H72 -> 3591741242 | K24: =损益现金流!I72 -> 3589995076 | ... M24: =损益现金流!K72 -> 3255541569
A26: 股本 | B26: =D26 -> 2609743532 | C26: =D26 -> 2609743532 | D26: =balance!C61 -> 2609743532 | E26: =balance!D61 -> 2609743532 | F26: =balance!E61 -> 2609743532 | G26: =balance!F61 -> 2609743532 | H26: =balance!G61 -> 2508617532 | I26: =balance!H61 -> 2508617532 | J26: =balance!I61 -> 2508617532 | K26: =balance!J61 -> 2508617532 | ... M26: =balance!L61 -> 2508617532
A28: 主营收入 | D28: =收入成本!B3 -> 38710428679 | E28: =收入成本!C3 -> 32650176898 | F28: =收入成本!D3 -> 27650978801 | G28: =收入成本!E3 -> 23261134069 | H28: =收入成本!F3 -> 19641289272 | I28: =收入成本!G3 -> 20765088255 | J28: =收入成本!H3 -> 19883838974 | K28: =收入成本!I3 -> 18190913985 | ... M28: =收入成本!K3 -> 13272702952
A29: 主营成本 | D29: =收入成本!B8 -> 24922427939 | E29: =收入成本!C8 -> 21310091980 | F29: =收入成本!D8 -> 18410110199 | G29: =收入成本!E8 -> 15039848812 | H29: =收入成本!F8 -> 11944882127 | I29: =收入成本!G8 -> 13060926884 | J29: =收入成本!H8 -> 11488667084 | K29: =收入成本!I8 -> 10484369082 | ... M29: =收入成本!K8 -> 7696406162
A30: 费用 | D30: =SUM(损益现金流!B5:B8) -> 6032289023 | E30: =SUM(损益现金流!C5:C8) -> 5667759562 | F30: =SUM(损益现金流!D5:D8) -> 4967587622 | G30: =SUM(损益现金流!E5:E8) -> 4297003585 | H30: =SUM(损益现金流!F5:F8) -> 4564753107 | I30: =SUM(损益现金流!G5:G8) -> 4677876806 | J30: =SUM(损益现金流!H5:H8) -> 4621537694 | K30: =SUM(损益现金流!I5:I8) -> 4075393078 | ... M30: =SUM(损益现金流!K5:K8) -> 3006403460
A31: 研发费用 | D31: =损益现金流!B8 -> 1677751298 | E31: =损益现金流!C8 -> 1403030121 | F31: =损益现金流!D8 -> 1248592812 | G31: =损益现金流!E8 -> 997203019 | H31: =损益现金流!F8 -> 815579258 | I31: =损益现金流!G8 -> 813129835 | J31: =损益现金流!H8 -> 887721987 | K31: =损益现金流!I8 -> 803441192 | ... M31: =损益现金流!K8 -> 0
A32: 销售费用 | D32: =损益现金流!B6 -> 1180260909 | E32: =损益现金流!C6 -> 1538783486 | F32: =损益现金流!D6 -> 1350721298 | G32: =损益现金流!E6 -> 1150992397 | H32: =损益现金流!F6 -> 1474366072 | I32: =损益现金流!G6 -> 1481567161 | J32: =损益现金流!H6 -> 1467671276 | K32: =损益现金流!I6 -> 1274308845 | ... M32: =损益现金流!K6 -> 1020584621
A33: 管理费用 | D33: =损益现金流!B7 -> 2888289768 | E33: =损益现金流!C7 -> 2486049334 | F33: =损益现金流!D7 -> 2142932036 | G33: =损益现金流!E7 -> 1944179027 | H33: =损益现金流!F7 -> 2076624937 | I33: =损益现金流!G7 -> 2185363063 | J33: =损益现金流!H7 -> 2063072209 | K33: =损益现金流!I7 -> 1797379424 | ... M33: =损益现金流!K7 -> 1873364984
A34: 损耗 | D34: =SUM(损益现金流!B11:B13) -> -98548679 | E34: =SUM(损益现金流!C11:C13) -> -220776671 | F34: =SUM(损益现金流!D11:D13) -> -150481522 | G34: =SUM(损益现金流!E11:E13) -> -23928049 | H34: =SUM(损益现金流!F11:F13) -> 38157119 | I34: =SUM(损益现金流!G11:G13) -> -20103858 | J34: =SUM(损益现金流!H11:H13) -> -51746308 | K34: =SUM(损益现金流!I11:I13) -> -31328690 | ... M34: =SUM(损益现金流!K11:K13) -> -11540935
A35: 其他收益 | D35: =损益现金流!B10 -> 400415185 | E35: =损益现金流!C10 -> 262917177 | F35: =损益现金流!D10 -> 215071387 | G35: =损益现金流!E10 -> 242337506 | H35: =损益现金流!F10 -> 352820556 | I35: =损益现金流!G10 -> 181754102 | J35: =损益现金流!H10 -> 146750220 | K35: =损益现金流!I10 -> 190690589 | ... M35: =损益现金流!K10 -> 0
A36: 现金收益 | D36: =损益现金流!B20 -> 924966003 | E36: =损益现金流!C20 -> 602544066 | F36: =损益现金流!D20 -> 231495735 | G36: =损益现金流!E20 -> 195413923 | H36: =损益现金流!F20 -> 348762592 | I36: =损益现金流!G20 -> 336984661 | J36: =损益现金流!H20 -> 335452093 | K36: =损益现金流!I20 -> 137540567 | ... M36: =损益现金流!K20 -> 16915996
A37: 股权收益 | D37: =损益现金流!B25 -> -15801862 | E37: =损益现金流!C25 -> 4290148 | F37: =损益现金流!D25 -> 20962737 | G37: =损益现金流!E25 -> 26975045 | H37: =损益现金流!F25 -> 11843754 | I37: =损益现金流!G25 -> -5932899 | J37: =损益现金流!H25 -> 667776495 | K37: =损益现金流!I25 -> 23390958 | ... M37: =损益现金流!K25 -> 23781843
A38: 利息支出 | D38: =损益现金流!B31 -> 288507082 | E38: =损益现金流!C31 -> 288319603 | F38: =损益现金流!D31 -> 288122259 | G38: =损益现金流!E31 -> 318940791 | H38: =损益现金流!F31 -> 354752403 | I38: =损益现金流!G31 -> 432679520 | J38: =损益现金流!H31 -> 376230473 | K38: =损益现金流!I31 -> 182373020 | ... M38: =损益现金流!K31 -> 190512029
A39: 财务费用 | D39: =损益现金流!B32 -> 35964048 | E39: =损益现金流!C32 -> -361719066 | F39: =损益现金流!D32 -> -1036725297 | G39: =损益现金流!E32 -> 536834250 | H39: =损益现金流!F32 -> 429822814 | I39: =损益现金流!G32 -> -127469129 | J39: =损益现金流!H32 -> -250823052 | K39: =损益现金流!I32 -> 393023828 | ... M39: =损益现金流!K32 -> -459846707
A40: 其他业务
A41: 收入 | D41: =收入成本!B17 -> 541228588 | E41: =收入成本!C17 -> 510819743 | F41: =收入成本!D17 -> 447775365 | G41: =收入成本!E17 -> 341929292 | H41: =收入成本!F17 -> 265304196 | I41: =收入成本!G17 -> 338789268 | J41: =收入成本!H17 -> 341146746 | K41: =收入成本!I17 -> 522120989 | ... M41: =收入成本!K17 -> 300792103
A42: 成本 | D42: =收入成本!B18 -> 108449502 | E42: =收入成本!C18 -> 114234160 | F42: =收入成本!D18 -> 125334935 | G42: =收入成本!E18 -> 89204424 | H42: =收入成本!F18 -> 97335416 | I42: =收入成本!G18 -> 136627509 | J42: =收入成本!H18 -> 114387863 | K42: =收入成本!I18 -> 228242734 | ... M42: =收入成本!K18 -> 117937075
A43: 营业外
A44: 收入 | D44: =损益现金流!B15 -> 35905331 | E44: =损益现金流!C15 -> 49843149 | F44: =损益现金流!D15 -> 80855034 | G44: =损益现金流!E15 -> 217974835 | H44: =损益现金流!F15 -> 57628048 | I44: =损益现金流!G15 -> 109494454 | J44: =损益现金流!H15 -> 60687441 | K44: =损益现金流!I15 -> 27172108 | ... M44: =损益现金流!K15 -> 129935252
A45: 成本 | D45: =损益现金流!B16 -> 120136061 | E45: =损益现金流!C16 -> 125106357 | F45: =损益现金流!D16 -> 163122132 | G45: =损益现金流!E16 -> 161162665 | H45: =损益现金流!F16 -> 214664627 | I45: =损益现金流!G16 -> 294294341 | J45: =损益现金流!H16 -> 71545321 | K45: =损益现金流!I16 -> 17376997 | ... M45: =损益现金流!K16 -> 138450464
A46: 所得税 | D46: =损益现金流!B33 -> 1486781220 | E46: =损益现金流!C33 -> 1086913641 | F46: =损益现金流!D33 -> 826310042 | G46: =损益现金流!E33 -> 675861301 | H46: =损益现金流!F33 -> 511144107 | I46: =损益现金流!G33 -> 332955880 | J46: =损益现金流!H33 -> 855187629 | K46: =损益现金流!I33 -> 531479253 | ... M46: =损益现金流!K33 -> 435226131
A49: 盈利结构
A50: 主营收入 | D50: =D28 -> 38710428679 | E50: =E28 -> 32650176898 | F50: =F28 -> 27650978801 | G50: =G28 -> 23261134069 | H50: =H28 -> 19641289272 | I50: =I28 -> 20765088255 | J50: =J28 -> 19883838974 | K50: =K28 -> 18190913985 | ... M50: =M28 -> 13272702952
A51: 主营成本 | D51: =D29 -> 24922427939 | E51: =E29 -> 21310091980 | F51: =F29 -> 18410110199 | G51: =G29 -> 15039848812 | H51: =H29 -> 11944882127 | I51: =I29 -> 13060926884 | J51: =J29 -> 11488667084 | K51: =K29 -> 10484369082 | ... M51: =M29 -> 7696406162
A52: 费用 | D52: =D30 -> 6032289023 | E52: =E30 -> 5667759562 | F52: =F30 -> 4967587622 | G52: =G30 -> 4297003585 | H52: =H30 -> 4564753107 | I52: =I30 -> 4677876806 | J52: =J30 -> 4621537694 | K52: =K30 -> 4075393078 | ... M52: =M30 -> 3006403460
A53: 损耗 | D53: =D34 -> -98548679 | E53: =E34 -> -220776671 | F53: =F34 -> -150481522 | G53: =G34 -> -23928049 | H53: =H34 -> 38157119 | I53: =I34 -> -20103858 | J53: =J34 -> -51746308 | K53: =K34 -> -31328690 | ... M53: =M34 -> -11540935
A54: 其他收益 | D54: =D35 -> 400415185 | E54: =E35 -> 262917177 | F54: =F35 -> 215071387 | G54: =G35 -> 242337506 | H54: =H35 -> 352820556 | I54: =I35 -> 181754102 | J54: =J35 -> 146750220 | K54: =K35 -> 190690589 | ... M54: =M35 -> 0
A55: 现金收益 | D55: =D36 -> 924966003 | E55: =E36 -> 602544066 | F55: =F36 -> 231495735 | G55: =G36 -> 195413923 | H55: =H36 -> 348762592 | I55: =I36 -> 336984661 | J55: =J36 -> 335452093 | K55: =K36 -> 137540567 | ... M55: =M36 -> 16915996
A56: 利息支出 | D56: =D38 -> 288507082 | E56: =E38 -> 288319603 | F56: =F38 -> 288122259 | G56: =G38 -> 318940791 | H56: =H38 -> 354752403 | I56: =I38 -> 432679520 | J56: =J38 -> 376230473 | K56: =K38 -> 182373020 | ... M56: =M38 -> 190512029
A57: 财务费用 | D57: =D39 -> 35964048 | E57: =E39 -> -361719066 | F57: =F39 -> -1036725297 | G57: =G39 -> 536834250 | H57: =H39 -> 429822814 | I57: =I39 -> -127469129 | J57: =J39 -> -250823052 | K57: =K39 -> 393023828 | ... M57: =M39 -> -459846707
A58: 所得税 | D58: =D46 -> 1486781220 | E58: =E46 -> 1086913641 | F58: =F46 -> 826310042 | G58: =G46 -> 675861301 | H58: =H46 -> 511144107 | I58: =I46 -> 332955880 | J58: =J46 -> 855187629 | K58: =K46 -> 531479253 | ... M58: =M46 -> 435226131
A59: 业务利润 | B59: =D59*1.3 -> 9.3226794e+09 | C59: =D59*1.15 -> 8.2469857e+09 | D59: =D50-D51-D52+D53+D54+D55-D56-D57-D58 -> 7171291876 | E59: =E50-E51-E52+E53+E54+E55-E56-E57-E58 -> 5303495750 | F59: =F50-F51-F52+F53+F54+F55-F56-F57-F58 -> 4491659576 | G59: =G50-G51-G52+G53+G54+G55-G56-G57-G58 -> 2806468710 | H59: =H50-H51-H52+H53+H54+H55-H56-H57-H58 -> 2575674981 | I59: =I50-I51-I52+I53+I54+I55-I56-I57-I58 -> 2886753199 | J59: =J50-J51-J52+J53+J54+J55-J56-J57-J58 -> 3223495151 | K59: =K50-K51-K52+K53+K54+K55-K56-K57-K58 -> 2821178190 | ... M59: =M50-M51-M52+M53+M54+M55-M56-M57-M58 -> 2409376938
A60: 股权收益 | D60: =D37 -> -15801862 | E60: =E37 -> 4290148 | F60: =F37 -> 20962737 | G60: =G37 -> 26975045 | H60: =H37 -> 11843754 | I60: =I37 -> -5932899 | J60: =J37 -> 667776495 | K60: =K37 -> 23390958 | ... M60: =M37 -> 23781843
A61: 其他业务利润 | D61: =D41-D42 -> 432779086 | E61: =E41-E42 -> 396585583 | F61: =F41-F42 -> 322440430 | G61: =G41-G42 -> 252724868 | H61: =H41-H42 -> 167968780 | I61: =I41-I42 -> 202161759 | J61: =J41-J42 -> 226758883 | K61: =K41-K42 -> 293878255 | ... M61: =M41-M42 -> 182855028
A62: 营业外利润 | D62: =D44-D45 -> -84230730 | E62: =E44-E45 -> -75263208 | F62: =F44-F45 -> -82267098 | G62: =G44-G45 -> 56812170 | H62: =H44-H45 -> -157036579 | I62: =I44-I45 -> -184799887 | J62: =J44-J45 -> -10857880 | K62: =K44-K45 -> 9795111 | ... M62: =M44-M45 -> -8515212
A63: 净利润 | D63: =SUM(D59:D62) -> 7504038370 | E63: =SUM(E59:E62) -> 5629108273 | F63: =SUM(F59:F62) -> 4752795645 | G63: =SUM(G59:G62) -> 3142980793 | H63: =SUM(H59:H62) -> 2598450936 | I63: =SUM(I59:I62) -> 2898182172 | J63: =SUM(J59:J62) -> 4107172649 | K63: =SUM(K59:K62) -> 3148242514 | ... M63: =SUM(M59:M62) -> 2607498597
A64: 分红 | D64: =D17 -> 4.6975384e+09 | E64: =E17 -> 3.3926666e+09 | F64: =F17 -> 3262179415 | G64: =G17 -> 2609743532 | H64: =H17 -> 1957307649 | I64: =I17 -> 1881463149 | J64: =J17 -> 2884910162 | K64: =K17 -> 1881463149 | ... M64: =M17 -> 1881463149
A65: 利润留存 | D65: =D63-D64 -> 2.8065e+09 | E65: =E63-E64 -> 2.2364417e+09 | F65: =F63-F64 -> 1490616230 | G65: =G63-G64 -> 533237261 | H65: =H63-H64 -> 641143287 | I65: =I63-I64 -> 1016719023 | J65: =J63-J64 -> 1222262487 | K65: =K63-K64 -> 1266779365 | ... M65: =M63-M64 -> 726035448
A66: 折旧摊销 | D66: =D23 -> 2727498647 | E66: =E23 -> 2522443359 | F66: =F23 -> 2345067457 | G66: =G23 -> 2251652666 | H66: =H23 -> 2242004968 | I66: =I23 -> 2130158309 | J66: =J23 -> 1687167602 | K66: =K23 -> 1398392498 | ... M66: =M23 -> 1031900411
A67: CAPEX | D67: =D24 -> 5480872166 | E67: =E24 -> 4474711099 | F67: =F24 -> 3130253387 | G67: =G24 -> 2328511864 | H67: =H24 -> 1772542963 | I67: =I24 -> 2779502262 | J67: =J24 -> 3591741242 | K67: =K24 -> 3589995076 | ... M67: =M24 -> 3255541569
A68: 现金留存 | D68: =D65+D66-D67 -> 53126493 | E68: =E65+E66-E67 -> 2.8417394e+08 | F68: =F65+F66-F67 -> 705430300 | G68: =G65+G66-G67 -> 456378063 | H68: =H65+H66-H67 -> 1110605292 | I68: =I65+I66-I67 -> 367375070 | J68: =J65+J66-J67 -> -682311153 | K68: =K65+K66-K67 -> -924823213 | ... M68: =M65+M66-M67 -> -1497605710
A69: 业务现金 | D69: =D63+D66-D67 -> 4750664851 | E69: =E63+E66-E67 -> 3676840533 | F69: =F63+F66-F67 -> 3967609715 | G69: =G63+G66-G67 -> 3066121595 | H69: =H63+H66-H67 -> 3067912941 | I69: =I63+I66-I67 -> 2248838219 | J69: =J63+J66-J67 -> 2202599009 | K69: =K63+K66-K67 -> 956639936 | ... M69: =M63+M66-M67 -> 383857439
A71: 经营周转
A72: 毛利率 | D72: =1-D29/D28 -> 0.35618311 | E72: =1-E29/E28 -> 0.34732078 | F72: =1-F29/F28 -> 0.3341968 | G72: =1-G29/G28 -> 0.35343441 | H72: =1-H29/H28 -> 0.39184837 | I72: =1-I29/I28 -> 0.3710151 | J72: =1-J29/J28 -> 0.42221082 | K72: =1-K29/K28 -> 0.42364803 | ... M72: =1-M29/M28 -> 0.42013272
A73: 费率 | D73: =D30/D28 -> 0.15583111 | E73: =E30/E28 -> 0.17359047 | F73: =F30/F28 -> 0.17965323 | G73: =G30/G28 -> 0.18472889 | H73: =H30/H28 -> 0.23240598 | I73: =I30/I28 -> 0.22527604 | J73: =J30/J28 -> 0.23242683 | K73: =K30/K28 -> 0.22403454 | ... M73: =M30/M28 -> 0.22651026
A74: 研发费率 | D74: =D31/D28 -> 0.043341067 | E74: =E31/E28 -> 0.042971593 | F74: =F31/F28 -> 0.045155465 | G74: =G31/G28 -> 0.042869923 | H74: =H31/H28 -> 0.041523713 | I74: =I31/I28 -> 0.039158506 | J74: =J31/J28 -> 0.044645402 | K74: =K31/K28 -> 0.04416717 | ... M74: =M31/M28 -> 0
A75: 销售费率 | D75: =D32/D28 -> 0.030489482 | E75: =E32/E28 -> 0.047129407 | F75: =F32/F28 -> 0.048848951 | G75: =G32/G28 -> 0.049481353 | H75: =H32/H28 -> 0.075064628 | I75: =I32/I28 -> 0.071348946 | J75: =J32/J28 -> 0.073812269 | K75: =K32/K28 -> 0.070051942 | ... M75: =M32/M28 -> 0.076893503
A76: 管理费率 | D76: =D33/D28 -> 0.074612704 | E76: =E33/E28 -> 0.076141987 | F76: =F33/F28 -> 0.077499319 | G76: =G33/G28 -> 0.083580578 | H76: =H33/H28 -> 0.10572753 | I76: =I33/I28 -> 0.10524218 | J76: =J33/J28 -> 0.10375623 | K76: =K33/K28 -> 0.098806439 | ... M76: =M33/M28 -> 0.1411442
A77: 净利率 | D77: =D59/D28 -> 0.18525478 | E77: =E59/E28 -> 0.16243391 | F77: =F59/F28 -> 0.16244125 | G77: =G59/G28 -> 0.12065055 | H77: =H59/H28 -> 0.13113574 | I77: =I59/I28 -> 0.13901955 | J77: =J59/J28 -> 0.16211634 | K77: =K59/K28 -> 0.15508722 | ... M77: =M59/M28 -> 0.18152873
A79: 应收占比 | D79: =D6/D28 -> 0.23170668 | E79: =E6/E28 -> 0.22958555 | F79: =F6/F28 -> 0.19753249 | G79: =G6/G28 -> 0.18701245 | H79: =H6/H28 -> 0.19112419 | I79: =I6/I28 -> 0.16746571 | J79: =J6/J28 -> 0.2164626 | K79: =K6/K28 -> 0.25494288 | ... M79: =M6/M28 -> 0.25105312
A80: 应收周转 | D80: =D28/D6 -> 4.3158013 | E80: =E28/E6 -> 4.3556749 | F80: =F28/F6 -> 5.0624584 | G80: =G28/G6 -> 5.3472375 | H80: =H28/H6 -> 5.2322001 | I80: =I28/I6 -> 5.9713716 | J80: =J28/J6 -> 4.6197357 | K80: =K28/K6 -> 3.9224473 | ... M80: =M28/M6 -> 3.9832208
A81: 存货周转 | D81: =D29/D8 -> 4.1741817 | E81: =E29/E8 -> 4.1430182 | F81: =F29/F8 -> 3.4071594 | G81: =G29/G8 -> 3.4757754 | H81: =H29/H8 -> 3.640634 | I81: =I29/I8 -> 3.9814251 | J81: =J29/J8 -> 3.5439817 | K81: =K29/K8 -> 3.5245398 | ... M81: =M29/M8 -> 2.7336925
A82: 应付（预付）占比 | D82: =(D12-D7)/D29 -> 0.22059005 | E82: =(E12-E7)/E29 -> 0.24431885 | F82: =(F12-F7)/F29 -> 0.21280563 | G82: =(G12-G7)/G29 -> 0.19343698 | H82: =(H12-H7)/H29 -> 0.19192153 | I82: =(I12-I7)/I29 -> 0.14354401 | J82: =(J12-J7)/J29 -> 0.19542939 | K82: =(K12-K7)/K29 -> 0.21036801 | ... M82: =(M12-M7)/M29 -> 0.15467733
A83: 预收占比 | D83: =D11/D28 -> 0.02085517 | E83: =E11/E28 -> 0.029986585 | F83: =F11/F28 -> 0.033690866 | G83: =G11/G28 -> 0.0371322 | H83: =H11/H28 -> 0.038504708 | I83: =I11/I28 -> 0.03348891 | J83: =J11/J28 -> 0.029898809 | K83: =K11/K28 -> 0.024313395 | ... M83: =M11/M28 -> 0.0025605556
A84: 利息支出/业务利润 | D84: =D56/D59 -> 0.040230838 | E84: =E56/E59 -> 0.054364068 | F84: =F56/F59 -> 0.064146059 | G84: =G56/G59 -> 0.11364488 | H84: =H56/H59 -> 0.13773182 | I84: =I56/I59 -> 0.14988449 | J84: =J56/J59 -> 0.11671507 | K84: =K56/K59 -> 0.064644275 | ... M84: =M56/M59 -> 0.079071077
A85: 折旧摊销/长期资产 | D85: =D23/D9 -> 0.10522046 | E85: =E23/E9 -> 0.11275246 | F85: =F23/F9 -> 0.11702168 | G85: =G23/G9 -> 0.11907709 | H85: =H23/H9 -> 0.11751395 | I85: =I23/I9 -> 0.10569614 | J85: =J23/J9 -> 0.091444125 | K85: =K23/K9 -> 0.085733488 | ... M85: =M23/M9 -> 0.08567758
A87: 资产结构
A88: 现金资产 | D88: =D3/D2 -> 0.32746787 | E88: =E3/E2 -> 0.35032118 | F88: =F3/F2 -> 0.35781121 | G88: =G3/G2 -> 0.34493079 | H88: =H3/H2 -> 0.27097614 | I88: =I3/I2 -> 0.25759746 | J88: =J3/J2 -> 0.19717862 | K88: =K3/K2 -> 0.21408199 | ... M88: =M3/M2 -> 0.24020391
A89: 股权资产 | D89: =D4/D2 -> 0.0082868432 | E89: =E4/E2 -> 0.0048135407 | F89: =F4/F2 -> 0.0064530864 | G89: =G4/G2 -> 0.0066572605 | H89: =H4/H2 -> 0.0068902636 | I89: =I4/I2 -> 0.0051461318 | J89: =J4/J2 -> 0.0059650749 | K89: =K4/K2 -> 0.0029923957 | ... M89: =M4/M2 -> 0.001885049
A90: 经营资产 | D90: =D5/D2 -> 0.25444234 | E90: =E5/E2 -> 0.24982108 | F90: =F5/F2 -> 0.24100289 | G90: =G5/G2 -> 0.22618918 | H90: =H5/H2 -> 0.22559979 | I90: =I5/I2 -> 0.21818515 | J90: =J5/J2 -> 0.26191799 | K90: =K5/K2 -> 0.27194609 | ... M90: =M5/M2 -> 0.26913075
A91: 长期资产 | D91: =D9/D2 -> 0.40980295 | E91: =E9/E2 -> 0.39504421 | F91: =F9/F2 -> 0.39473282 | G91: =G9/G2 -> 0.42222277 | H91: =H9/H2 -> 0.4965338 | I91: =I9/I2 -> 0.51907126 | J91: =J9/J2 -> 0.53493831 | K91: =K9/K2 -> 0.51097952 | ... M91: =M9/M2 -> 0.48878029
A92: 负债结构
A93: 经营负债 | D93: =(D10-D13)/D2 -> 0.19877444 | E93: =(E10-E13)/E2 -> 0.18864708 | F93: =(F10-F13)/F2 -> 0.17269299 | G93: =(G10-G13)/G2 -> 0.16266964 | H93: =(H10-H13)/H2 -> 0.16651559 | I93: =(I10-I13)/I2 -> 0.15643344 | J93: =(J10-J13)/J2 -> 0.17098325 | K93: =(K10-K13)/K2 -> 0.16298317 | ... M93: =(M10-M13)/M2 -> 0.14891024
A94: 有息负债 | D94: =D13/D2 -> 0.23706414 | E94: =E13/E2 -> 0.25668055 | F94: =F13/F2 -> 0.2563059 | G94: =G13/G2 -> 0.25021042 | H94: =H13/H2 -> 0.27156691 | I94: =I13/I2 -> 0.29318981 | J94: =J13/J2 -> 0.24364082 | K94: =K13/K2 -> 0.24812764 | ... M94: =M13/M2 -> 0.19246926
A95: 权益结构
A96: 资本投入 | D96: =D15/D2 -> 0.19461945 | E96: =E15/E2 -> 0.21738312 | F96: =F15/F2 -> 0.24248771 | G96: =G15/G2 -> 0.27488051 | H96: =H15/H2 -> 0.22724378 | I96: =I15/I2 -> 0.22489138 | J96: =J15/J2 -> 0.25316279 | K96: =K15/K2 -> 0.27357472 | ... M96: =M15/M2 -> 0.35459513
A97: 利润留存 | D97: =D16/D2 -> 0.2944627 | E97: =E16/E2 -> 0.26500186 | F97: =F16/F2 -> 0.25586831 | G97: =G16/G2 -> 0.2511 | H97: =H16/H2 -> 0.26820865 | I97: =I16/I2 -> 0.25314542 | J97: =J16/J2 -> 0.26530027 | K97: =K16/K2 -> 0.26165572 | ... M97: =M16/M2 -> 0.26782141
A99: 营收YoY | D99: =D28/E28-1 -> 0.18561161 | E99: =E28/F28-1 -> 0.18079642 | F99: =F28/G28-1 -> 0.18872015 | G99: =G28/H28-1 -> 0.18429772 | H99: =H28/I28-1 -> -0.054119634 | I99: =I28/J28-1 -> 0.044319876 | J99: =J28/K28-1 -> 0.093064317 | K99: =K28/L28-1 -> 0.11665322 | L99: =L28/M28-1 -> 0.22737373
A100: 业务净利润YoY | D100: =D63/E63-1 -> 0.33307764 | E100: =E63/F63-1 -> 0.18437835 | F100: =F63/G63-1 -> 0.51219367 | G100: =G63/H63-1 -> 0.20955941 | H100: =H63/I63-1 -> -0.10342043 | I100: =I63/J63-1 -> -0.29436076 | J100: =J63/K63-1 -> 0.30459221 | K100: =K63/L63-1 -> 0.0017583361 | L100: =L63/M63-1 -> 0.20526107
A102: 资产YoY | D102: =D2/E2-1 -> 0.11696499 | E102: =E2/F2-1 -> 0.11548547 | F102: =F2/G2-1 -> 0.13358533 | G102: =G2/H2-1 -> 0.16555618 | H102: =H2/I2-1 -> -0.010370667 | I102: =I2/J2-1 -> 0.12571139 | J102: =J2/K2-1 -> 0.080497128 | K102: =K2/L2-1 -> 0.068809458 | L102: =L2/M2-1 -> 0.21204265
A103: 现金 | D103: =(D3-E3)/(D2-E2)*D102 -> 0.015448966 | E103: =(E3-F3)/(E2-F2)*E102 -> 0.032966973 | F103: =(F3-G3)/(F2-G2)*F102 -> 0.06067875 | G103: =(G3-H3)/(G2-H2)*G102 -> 0.13106007 | H103: =(H3-I3)/(H2-I2)*H102 -> 0.010568477 | I103: =(I3-J3)/(I2-J2)*I102 -> 0.092801769 | J103: =(J3-K3)/(J2-K2)*J102 -> -0.0010310544 | K103: =(K3-L3)/(K2-L2)*K102 -> -0.012704841 | L103: =(L3-M3)/(L2-M2)*L102 -> 0.052525844
A104: 投资 | D104: =(D4-E4)/(D2-E2)*D102 -> 0.004442573 | E104: =(E4-F4)/(E2-F2)*E102 -> -0.0010836516 | F104: =(F4-G4)/(F2-G2)*F102 -> 0.00065786359 | G104: =(G4-H4)/(G2-H2)*G102 -> 0.00086914756 | H104: =(H4-I4)/(H2-I2)*H102 -> 0.0016726752 | I104: =(I4-J4)/(I2-J2)*I102 -> -0.00017201576 | J104: =(J4-K4)/(J2-K2)*J102 -> 0.0034528506 | K104: =(K4-L4)/(K2-L2)*K102 -> -0.00020144971 | L104: =(L4-M4)/(L2-M2)*L102 -> 0.0022355937
A105: 运营资产 | D105: =(D5-E5)/(D2-E2)*D102 -> 0.034382112 | E105: =(E5-F5)/(E2-F2)*E102 -> 0.037668895 | F105: =(F5-G5)/(F2-G2)*F102 -> 0.047008157 | G105: =(G5-H5)/(G2-H2)*G102 -> 0.038036402 | H105: =(H5-I5)/(H2-I2)*H102 -> 0.0050750249 | I105: =(I5-J5)/(I2-J2)*I102 -> -0.016304485 | J105: =(J5-K5)/(J2-K2)*J102 -> 0.011055544 | K105: =(K5-L5)/(K2-L2)*K102 -> 0.024517694 | L105: =(L5-M5)/(L2-M2)*L102 -> 0.053443324
A106: 长期资产 | D106: =(D9-E9)/(D2-E2)*D102 -> 0.06269134 | E106: =(E9-F9)/(E2-F2)*E102 -> 0.045933258 | F106: =(F9-G9)/(F2-G2)*F102 -> 0.02524056 | G106: =(G9-H9)/(G2-H2)*G102 -> -0.0044094398 | H106: =(H9-I9)/(H2-I2)*H102 -> -0.027686844 | I106: =(I9-J9)/(I2-J2)*I102 -> 0.049386119 | J106: =(J9-K9)/(J2-K2)*J102 -> 0.067019788 | K106: =(K9-L9)/(K2-L2)*K102 -> 0.057198054 | L106: =(L9-M9)/(L2-M2)*L102 -> 0.10383789
A107: 权益YoY | D107: =D14/E14-1 -> 0.13607345 | E107: =E14/F14-1 -> 0.083586287 | F107: =F14/G14-1 -> 0.1024638 | G107: =G14/H14-1 -> 0.2178323 | H107: =H14/I14-1 -> 0.010380688 | I107: =I14/J14-1 -> 0.058405961 | J107: =J14/K14-1 -> 0.074050978 | K107: =K14/L14-1 -> 0.042094636 | L107: =L14/M14-1 -> 0.098901784
A108: 资本投入 | D108: =(D15-E15)/(D14-E14)*D107 -> 0 | E108: =(E15-F15)/(E14-F14)*E107 -> 0 | F108: =(F15-G15)/(F14-G14)*F107 -> 0 | G108: =(G15-H15)/(G14-H14)*G107 -> 0.16576258 | H108: =(H15-I15)/(H14-I14)*H107 -> -7.7552234e-06 | I108: =(I15-J15)/(I14-J14)*I107 -> 0 | J108: =(J15-K15)/(J14-K14)*J107 -> -5.6120183e-05 | K108: =(K15-L15)/(K14-L14)*K107 -> -0.00025611821 | L108: =(L15-M15)/(L14-M14)*L107 -> -1.0926243e-05
A109: 未分配利润 | D109: =(D16-E16)/(D14-E14)*D107 -> 0.11520794 | E109: =(E16-F16)/(E14-F14)*E107 -> 0.069592544 | F109: =(F16-G16)/(F14-G14)*F107 -> 0.06633833 | G109: =(G16-H16)/(G14-H14)*G107 -> 0.043533997 | H109: =(H16-I16)/(H14-I14)*H107 -> 0.022315125 | I109: =(I16-J16)/(I14-J14)*I107 -> 0.033599616 | J109: =(J16-K16)/(J14-K14)*J107 -> 0.042453598 | K109: =(K16-L16)/(K14-L14)*K107 -> 0.04331814 | L109: =(L16-M16)/(L14-M14)*L107 -> 0.059184867
A110: 负债YoY | D110: =D10/E10-1 -> 0.093164688 | E110: =E10/F10-1 -> 0.15794356 | F110: =F10/G10-1 -> 0.17784048 | G110: =G10/H10-1 -> 0.098502915 | H110: =H10/I10-1 -> -0.035772075 | I110: =I10/J10-1 -> 0.22073476 | J110: =J10/K10-1 -> 0.089730814 | K110: =K10/L10-1 -> 0.10955388 | L110: =L10/M10-1 -> 0.40601917
A111: 预收 | D111: =(D11-E11)/(D10-E10)*D110 -> -0.0068105054 | E111: =(E11-F11)/(E10-F10)*E110 -> 0.0021801487 | F111: =(F11-G11)/(F10-G10)*F110 -> 0.0036693034 | G111: =(G11-H11)/(G10-H10)*G110 -> 0.0063836973 | H111: =(H11-I11)/(H10-I10)*H110 -> 0.0034874983 | I111: =(I11-J11)/(I10-J10)*I110 -> 0.0070554588 | J111: =(J11-K11)/(J10-K10)*J110 -> 0.011599476 | K111: =(K11-L11)/(K10-L10)*K110 -> 0.035582703 | L111: =(L11-M11)/(L10-M10)*L110 -> -0.0014919223
...
