Workbook

Sheet balance sheet（处理后）
C1: 2024.12.31 | D1: 2023.12.31 | E1: 2022.12.31 | F1: 2021.12.31 | G1: 2020.12.31 | H1: 2019.12.31
A2: 资产 | C2: =C3+C10+C15+C26 -> 1.5912889e+10 | D2: =D3+D10+D15+D26 -> 1.3974021e+10 | E2: =E3+E10+E15+E26 -> 1.2057677e+10 | F2: =F3+F10+F15+F26 -> 1.0425669e+10 | G2: =G3+G10+G15+G26 -> 8.5115862e+09 | H2: =H3+H10+H15+H26 -> 6.8439935e+09
A3: 金融资产 | C3: =SUM(C4:C8) -> 1.2812479e+10 | D3: =SUM(D4:D8) -> 1.1392118e+10 | E3: =SUM(E4:E8) -> 1.0293767e+10 | F3: =SUM(F4:F8) -> 9.2193082e+09 | G3: =SUM(G4:G8) -> 7.6442103e+09 | H3: =SUM(H4:H8) -> 6.2955176e+09
B4: 货币资金 | C4: 8.9793629e+08 | D4: 3.4781593e+09 | E4: 7.0154461e+09 | F4: 1.2539586e+09 | G4: 1.0035041e+09 | H4: 7.4923668e+08
B5: 交易性金融资产 | C5: 1.3841518e+09 | D5: 2.5707621e+09 | H5: 15500000
B6: 理财产品 | E6: 1.1921074e+09 | F6: 6.9418323e+09 | G6: 6.6254452e+09 | H6: 5.5206946e+09
B7: 定期存款/利息 | C7: =3168225913.95+7343591355.88 -> 1.0511817e+10 | D7: =1154634585.44+2249205659.64+1918453672.93 -> 5.3222939e+09 | E7: =962979425.76+1123233771.41 -> 2.0862132e+09 | F7: =150575.44+1023366805.62 -> 1.0235174e+09 | G7: 192343.26 | H7: 280.31
B8: 其他非流动金融资产 | C8: 18573510 | D8: 20902460 | G8: 15068687 | H8: 10086000
A10: 长期股权投资 | C10: =SUM(C11:C13) -> 1.5837826e+09 | D10: =SUM(D11:D13) -> 1.1148938e+09 | E10: =SUM(E11:E13) -> 4.913314e+08 | F10: =SUM(F11:F13) -> 1.6841795e+08 | G10: =SUM(G11:G13) -> 53083238 | H10: =SUM(H11:H13) -> 38612671
B11: 长期股权投资 | C11: 1.5630075e+09 | D11: 1.0940629e+09 | E11: 4.4409524e+08 | F11: 1.2319479e+08 | G11: 35832545 | H11: 21856850
B12: 其他权益工具投资 | C12: 19967434 | D12: 19754308 | E12: 19615452 | F12: 8800620 | G12: 9058955.2 | H12: 9642362.3
B13: 其他非流动金融资产（权益工具） | C13: 807695.81 | D13: 1076527.9 | E13: 27620704 | F13: 36422542 | G13: =6191738.29+2000000 -> 8191738.3 | H13: =7113458.54 -> 7113458.5
A15: 经营资产 | C15: =SUM(C16:C24) -> 7.2816093e+08 | D15: =SUM(D16:D24) -> 7.6115434e+08 | E15: =SUM(E16:E24) -> 647433732 | F15: =SUM(F16:F24) -> 5.3505509e+08 | G15: =SUM(G16:G24) -> 4.961692e+08 | H15: =SUM(H16:H24) -> 4.1410836e+08
B16: 应收票据 | C16: 5309651.7 | D16: 2080000 | E16: 3447750 | F16: 3667000 | G16: 2340900 | H16: 2086153.9
B17: 应收帐款 | C17: 5.0456706e+08 | D17: 5.6694035e+08 | E17: 4.9679152e+08 | F17: 4.1153132e+08 | G17: 3.9810848e+08 | H17: 3.4502336e+08
B18: 预付款项 | C18: 13981930 | D18: 21957493 | E18: 27596962 | F18: 25601542 | G18: 8383888.8 | H18: 5322052.8
B19: 其他应收款 | C19: 69650288 | D19: 49547645 | E19: 27086472 | F19: =36082150.16 -> 36082150 | G19: 41018315 | H19: 25502706
B20: 存货 | C20: 802036.62 | D20: 1412787.6 | E20: 1157966.9 | F20: 2296705.1 | G20: 1347945.7 | H20: 1428104.1
B21: 合同资产 | C21: 263087.25 | D21: 1627986.9 | E21: 2151316.3 | F21: 2293113.3
B22: 其他流动资产 | C22: 59813764 | D22: 50632903 | E22: =2005683.48+21437102.5+23108553.53 -> 46551340 | F22: 16749539 | G22: 7831649.1 | H22: 15766894
B23: 其他非流动资产 | C23: =16902633.88+21893267.98 -> 38795902 | D23: =15847661.8+10379190.9 -> 26226853 | E23: =13808232.72+7716198.73 -> 21524431 | F23: =7196666+10583485.34 -> 17780151 | G23: 21358676 | H23: 3919100
B24: 递延所得税资产 | C24: 34977206 | D24: 40728324 | E24: 21125978 | F24: 19053561 | G24: 15779343 | H24: 15059985
A26: 长期资产 | C26: =SUM(C27:C32) -> 7.8846634e+08 | D26: =SUM(D27:D32) -> 7.0585543e+08 | E26: =SUM(E27:E32) -> 6.2514484e+08 | F26: =SUM(F27:F32) -> 5.0288813e+08 | G26: =SUM(G27:G32) -> 3.1812341e+08 | H26: =SUM(H27:H32) -> 95754892
B27: 固定资产 | C27: 2.9665123e+08 | D27: 68991108 | E27: 82420787 | F27: 88342058 | G27: 61686373 | H27: 67165132
B28: 在建工程 | C28: 1.3495944e+08 | D28: 2.4805629e+08 | E28: 1.2064613e+08
B29: 使用权资产 | C29: 43404511 | D29: 70889834 | E29: 1.0705335e+08 | F29: 99376293
B30: 无形资产 | C30: 79351285 | D30: 87027526 | E30: 1.0229323e+08 | F30: 1.1798333e+08 | G30: 59044733 | H30: 17609109
B31: 商誉 | C31: 1.8466897e+08 | D31: 1.8466897e+08 | E31: 1.8466897e+08 | F31: 1.8466897e+08 | G31: 1.8466897e+08
B32: 长期待摊费用 | C32: 49430909 | D32: 46221703 | E32: 28062368 | F32: 12517470 | G32: 12723328 | H32: 10980651
A34: 负债 | C34: =C35+C49+C52 -> 4.4763191e+09 | D34: =D35+D49+D52 -> 3.9544151e+09 | E34: =E35+E49+E52 -> 3.2592856e+09 | F34: =F35+F49+F52 -> 2.6454601e+09 | G34: =G35+G49+G52 -> 1.6207629e+09 | H34: =H35+H49+H52 -> 7.7541323e+08
A35: 经营负债 | C35: =SUM(C36:C47) -> 4.363218e+09 | D35: =SUM(D36:D47) -> 3876009543 | E35: =SUM(E36:E47) -> 3.1240163e+09 | F35: =SUM(F36:F47) -> 2.5309469e+09 | G35: =SUM(G36:G47) -> 1.6207629e+09 | H35: =SUM(H36:H47) -> 7.7541323e+08
B36: 应付账款 | C36: 4.458657e+08 | D36: 4.5348455e+08 | E36: 3.0630474e+08 | F36: 2.1219664e+08 | G36: 1.4038947e+08 | H36: 60235681
B37: 预收款项 | H37: 4.3767363e+08
B38: 合同负债 | C38: 2.1355359e+09 | D38: 1.8918741e+09 | E38: 1.7312476e+09 | F38: 1.420876e+09 | G38: 8.3275063e+08
B39: 应付职工薪酬 | C39: 4.8106591e+08 | D39: 4.6359106e+08 | E39: 3.9433263e+08 | F39: 3.6030722e+08 | G39: 2.4994716e+08 | H39: 1.5529453e+08
B40: 应交税费 | C40: 80085593 | D40: 70268323 | E40: 45606445 | F40: 55460575 | G40: 1.1242866e+08 | H40: 37890686
B41: 其他应付款 | C41: 1.1666246e+08 | D41: 1.0367197e+08 | E41: 97531167 | F41: 90666378 | G41: 49333920 | H41: 35618022
B42: 其他流动负债 | C42: 1.0721531e+08 | D42: 1.3416301e+08 | E42: 1.0935069e+08 | F42: 88406222 | G42: 52964852
B43: 长期应付款 | D43: 56710317 | E43: 51723271 | F43: 47174781
B44: 预计负债 | D44: 10000000
B45: 递延收益 | C45: 2392855.7 | D45: 36640187 | E45: 43847197 | F45: 66634447 | G45: 83720563 | H45: 35553471
B46: 其他非流动负债 | C46: 9.433486e+08 | D46: 6.126389e+08 | E46: 3.1728137e+08 | F46: 1.7333984e+08 | G46: 84923225
B47: 递延所得税负债 | C47: 51045636 | D47: 42967086 | E47: 26791198 | F47: 15884781 | G47: 14304414 | H47: 13147214
A49: 短期负债 | C49: =SUM(C50:C51) -> 95902275 | D49: =SUM(D50:D51) -> 36734729 | E49: =SUM(E50:E51) -> 65846468 | F49: =SUM(F50:F51) -> 39796839 | G49: =SUM(G50:G51) -> 0 | H49: =SUM(H50:H51) -> 0
B50: 一年内到期的非流动负债 | C50: 95902275 | D50: 36734729 | E50: 65846468 | F50: 39796839
A52: 长期负债 | C52: =SUM(C53:C54) -> 17198900 | D52: =SUM(D53:D54) -> 41670797 | E52: =SUM(E53:E54) -> 69422848 | F52: =SUM(F53:F54) -> 74716362 | G52: =SUM(G53:G54) -> 0 | H52: =SUM(H53:H54) -> 0
B53: 租赁负债 | C53: 17198900 | D53: 41670797 | E53: 69422848 | F53: 74716362
A55: 所有者权益 | C55: =SUM(C56:C62) -> 1.143657e+10 | D55: =SUM(D56:D62) -> 1.0019606e+10 | E55: =SUM(E56:E62) -> 8.798391e+09 | F55: =SUM(F56:F62) -> 7.7802093e+09 | G55: =SUM(G56:G62) -> 6.8908233e+09 | H55: =SUM(H56:H62) -> 6.0685803e+09
B56: 股本 | C56: 462525643 | D56: 461723327 | E56: 461221529 | F56: 461000000 | G56: 461000000 | H56: 461000000
B57: 资本公积 | C57: 5.4407901e+09 | D57: 5.1777974e+09 | E57: 4.9416414e+09 | F57: 4.7475227e+09 | G57: 4.6419105e+09 | H57: 4.5882526e+09
B58: 库存股 | C58: -1.0002817e+08
B59: 其他综合收益 | C59: 19660493 | D59: 15457652 | E59: 11403623 | F59: -4213410.2 | G59: -680613.3 | H59: 6492873.1
B60: 盈余公积 | C60: 2.3126282e+08 | D60: 2.0075655e+08 | E60: 1.5297307e+08 | F60: 1.0703145e+08 | G60: 71827658 | H60: 59681243
B61: 未分配利润 | C61: 5.3013467e+09 | D61: 4.0930628e+09 | E61: 3.1570626e+09 | F61: 2.4081747e+09 | G61: 1.6808484e+09 | H61: 9.5315356e+08
B62: 少数股东权益 | C62: 81012067 | D62: 70808511 | E62: 74088799 | F62: 60693813 | G62: 35917358
C65: =C55+C34 -> 1.5912889e+10 | D65: =D55+D34 -> 1.3974021e+10 | E65: =E55+E34 -> 1.2057677e+10 | F65: =F55+F34 -> 1.0425669e+10 | G65: =G55+G34 -> 8.5115862e+09 | H65: =H55+H34 -> 6.8439935e+09
C69: =C65-C2 -> 0 | D69: =D65-D2 -> 0

Sheet balance
C1: 2024.12.31 | D1: 2023.12.31 | E1: 2022.12.31 | F1: 2021.12.31 | G1: 2020.12.31 | H1: 2019.12.31
A2: 资产 | C2: =C3+C11+C15+C25 -> 1.5912889e+10 | D2: =D3+D11+D15+D25 -> 1.3974021e+10 | E2: =E3+E11+E15+E25 -> 1.2057677e+10 | F2: =F3+F11+F15+F25 -> 1.0425669e+10 | G2: =G3+G11+G15+G25 -> 8.5115862e+09 | H2: =H3+H11+H15+H25 -> 6.8439935e+09
A3: 金融资产 | C3: =SUM(C4:C8) -> 1.2832701e+10 | D3: =SUM(D4:D8) -> 1.1397442e+10 | E3: =SUM(E4:E8) -> 1.0315291e+10 | F3: =SUM(F4:F9) -> 9.2370884e+09 | G3: =SUM(G4:G9) -> 7.6505003e+09 | H3: =SUM(H4:H9) -> 6.2893507e+09
B4: 货币资金 | C4: 8.9793629e+08 | D4: 3.4781593e+09 | E4: 7.0154461e+09 | F4: 1.2539586e+09 | G4: 1.0035041e+09 | H4: 7.4923668e+08
B5: 交易性金融资产 | C5: 1.3841518e+09 | D5: 2.5707621e+09 | E5: 1.1921074e+09 | F5: 6.9418323e+09 | G5: 6.6254452e+09 | H5: 5.5361946e+09
B6: 一年内到期的非流动资产 | C6: 77313613 | D6: 1.1546346e+09
B7: 其他流动资产 | C7: 3.0909123e+09 | D7: 2.2492057e+09 | E7: 9.6297943e+08
B8: 其他非流动资产 | C8: 7.3823873e+09 | D8: 1.9446805e+09 | E8: 1.1447582e+09 | F8: 1.041147e+09 | G8: 21358676 | H8: 3919100
B9: 应收利息 | F9: 150575.44 | G9: 192343.26 | H9: 280.31
A11: 长期股权投资 | C11: =SUM(C12:C14) -> 1.6023561e+09 | D11: =SUM(D12:D14) -> 1.1357962e+09 | E11: =SUM(E12:E14) -> 4.913314e+08 | F11: =SUM(F12:F14) -> 1.6841795e+08 | G11: =SUM(G12:G14) -> 68151925 | H11: =SUM(H12:H14) -> 48698671
B12: 长期股权投资 | C12: 1.5630075e+09 | D12: 1.0940629e+09 | E12: 4.4409524e+08 | F12: 1.2319479e+08 | G12: 35832545 | H12: 21856850
B13: 其他权益工具投资 | C13: 19967434 | D13: 19754308 | E13: 19615452 | F13: 8800620 | G13: 9058955.2 | H13: 9642362.3
B14: 其他非流动金融资产 | C14: 19381206 | D14: 21978988 | E14: 27620704 | F14: 36422542 | G14: 23260425 | H14: 17199459
A15: 经营资产 | C15: =SUM(C16:C23) -> 6.8936502e+08 | D15: =SUM(D16:D23) -> 7.3492749e+08 | E15: =SUM(E16:E23) -> 6.259093e+08 | F15: =SUM(F16:F23) -> 5.1727494e+08 | G15: =SUM(G16:G23) -> 4.7481052e+08 | H15: =SUM(H16:H23) -> 4.1018926e+08
B16: 应收票据 | C16: 5309651.7 | D16: 2080000 | E16: 3447750 | F16: 3667000 | G16: 2340900 | H16: 2086153.9
B17: 应收帐款 | C17: 5.0456706e+08 | D17: 5.6694035e+08 | E17: 4.9679152e+08 | F17: 4.1153132e+08 | G17: 3.9810848e+08 | H17: 3.4502336e+08
B18: 预付款项 | C18: 13981930 | D18: 21957493 | E18: 27596962 | F18: 25601542 | G18: 8383888.8 | H18: 5322052.8
B19: 其他应收款 | C19: 69650288 | D19: 49547645 | E19: 27086472 | F19: =36232725.6-F9 -> 36082150 | G19: =41210658.13-G9 -> 41018315 | H19: =25502986.03-H9 -> 25502706
B20: 存货 | C20: 802036.62 | D20: 1412787.6 | E20: 1157966.9 | F20: 2296705.1 | G20: 1347945.7 | H20: 1428104.1
B21: 合同资产 | C21: 263087.25 | D21: 1627986.9 | E21: 2151316.3 | F21: 2293113.3
B22: 其他流动资产 | C22: 59813764 | D22: 50632903 | E22: =1009530765.27-E7 -> 46551340 | F22: 16749539 | G22: 7831649.1 | H22: 15766894
B23: 递延所得税资产 | C23: 34977206 | D23: 40728324 | E23: 21125978 | F23: 19053561 | G23: 15779343 | H23: 15059985
A25: 长期资产 | C25: =SUM(C26:C31) -> 7.8846634e+08 | D25: =SUM(D26:D31) -> 7.0585543e+08 | E25: =SUM(E26:E31) -> 6.2514484e+08 | F25: =SUM(F26:F31) -> 5.0288813e+08 | G25: =SUM(G26:G31) -> 3.1812341e+08 | H25: =SUM(H26:H31) -> 95754892
B26: 固定资产 | C26: 2.9665123e+08 | D26: 68991108 | E26: 82420787 | F26: 88342058 | G26: 61686373 | H26: 67165132
B27: 在建工程 | C27: 1.3495944e+08 | D27: 2.4805629e+08 | E27: 1.2064613e+08
B28: 使用权资产 | C28: 43404511 | D28: 70889834 | E28: 1.0705335e+08 | F28: 99376293
B29: 无形资产 | C29: 79351285 | D29: 87027526 | E29: 1.0229323e+08 | F29: 1.1798333e+08 | G29: 59044733 | H29: 17609109
B30: 商誉 | C30: 1.8466897e+08 | D30: 1.8466897e+08 | E30: 1.8466897e+08 | F30: 1.8466897e+08 | G30: 1.8466897e+08
B31: 长期待摊费用 | C31: 49430909 | D31: 46221703 | E31: 28062368 | F31: 12517470 | G31: 12723328 | H31: 10980651
A33: 负债 | C33: =C34+C48+C51 -> 4.4763191e+09 | D33: =D34+D48+D51 -> 3.9544151e+09 | E33: =E34+E48+E51 -> 3.2592856e+09 | F33: =F34+F48+F51 -> 2.6454601e+09 | G33: =G34+G48+G51 -> 1.6207629e+09 | H33: =H34+H48+H51 -> 7.7541323e+08
A34: 经营负债 | C34: =SUM(C35:C46) -> 4.363218e+09 | D34: =SUM(D35:D46) -> 3876009543 | E34: =SUM(E35:E46) -> 3.1240163e+09 | F34: =SUM(F35:F46) -> 2.5309469e+09 | G34: =SUM(G35:G46) -> 1.6207629e+09 | H34: =SUM(H35:H46) -> 7.7541323e+08
B35: 应付账款 | C35: 4.458657e+08 | D35: 4.5348455e+08 | E35: 3.0630474e+08 | F35: 2.1219664e+08 | G35: 1.4038947e+08 | H35: 60235681
B36: 预收款项 | H36: 4.3767363e+08
B37: 合同负债 | C37: 2.1355359e+09 | D37: 1.8918741e+09 | E37: 1.7312476e+09 | F37: 1.420876e+09 | G37: 8.3275063e+08
B38: 应付职工薪酬 | C38: 4.8106591e+08 | D38: 4.6359106e+08 | E38: 3.9433263e+08 | F38: 3.6030722e+08 | G38: 2.4994716e+08 | H38: 1.5529453e+08
B39: 应交税费 | C39: 80085593 | D39: 70268323 | E39: 45606445 | F39: 55460575 | G39: 1.1242866e+08 | H39: 37890686
B40: 其他应付款 | C40: 1.1666246e+08 | D40: 1.0367197e+08 | E40: 97531167 | F40: 90666378 | G40: 49333920 | H40: 35618022
B41: 其他流动负债 | C41: 1.0721531e+08 | D41: 1.3416301e+08 | E41: 1.0935069e+08 | F41: 88406222 | G41: 52964852
B42: 长期应付款 | D42: 56710317 | E42: 51723271 | F42: 47174781
B43: 预计负债 | D43: 10000000
B44: 递延收益 | C44: 2392855.7 | D44: 36640187 | E44: 43847197 | F44: 66634447 | G44: 83720563 | H44: 35553471
B45: 其他非流动负债 | C45: 9.433486e+08 | D45: 6.126389e+08 | E45: 3.1728137e+08 | F45: 1.7333984e+08 | G45: 84923225
B46: 递延所得税负债 | C46: 51045636 | D46: 42967086 | E46: 26791198 | F46: 15884781 | G46: 14304414 | H46: 13147214
A48: 短期负债 | C48: =SUM(C49:C50) -> 95902275 | D48: =SUM(D49:D50) -> 36734729 | E48: =SUM(E49:E50) -> 65846468 | F48: =SUM(F49:F50) -> 39796839 | G48: =SUM(G49:G50) -> 0 | H48: =SUM(H49:H50) -> 0
B49: 一年内到期的非流动负债 | C49: 95902275 | D49: 36734729 | E49: 65846468 | F49: 39796839
A51: 长期负债 | C51: =SUM(C52:C53) -> 17198900 | D51: =SUM(D52:D53) -> 41670797 | E51: =SUM(E52:E53) -> 69422848 | F51: =SUM(F52:F53) -> 74716362 | G51: =SUM(G52:G53) -> 0 | H51: =SUM(H52:H53) -> 0
B52: 租赁负债 | C52: 17198900 | D52: 41670797 | E52: 69422848 | F52: 74716362
A54: 所有者权益 | C54: =SUM(C55:C61) -> 1.143657e+10 | D54: =SUM(D55:D61) -> 1.0019606e+10 | E54: =SUM(E55:E61) -> 8.798391e+09 | F54: =SUM(F55:F61) -> 7.7802093e+09 | G54: =SUM(G55:G61) -> 6.8908233e+09 | H54: =SUM(H55:H61) -> 6.0685803e+09
B55: 股本 | C55: 462525643 | D55: 461723327 | E55: 461221529 | F55: 461000000 | G55: 461000000 | H55: 461000000
B56: 资本公积 | C56: 5.4407901e+09 | D56: 5.1777974e+09 | E56: 4.9416414e+09 | F56: 4.7475227e+09 | G56: 4.6419105e+09 | H56: 4.5882526e+09
B57: 库存股 | C57: -1.0002817e+08
B58: 其他综合收益 | C58: 19660493 | D58: 15457652 | E58: 11403623 | F58: -4213410.2 | G58: -680613.3 | H58: 6492873.1
B59: 盈余公积 | C59: 2.3126282e+08 | D59: 2.0075655e+08 | E59: 1.5297307e+08 | F59: 1.0703145e+08 | G59: 71827658 | H59: 59681243
B60: 未分配利润 | C60: 5.3013467e+09 | D60: 4.0930628e+09 | E60: 3.1570626e+09 | F60: 2.4081747e+09 | G60: 1.6808484e+09 | H60: 9.5315356e+08
B61: 少数股东权益 | C61: 81012067 | D61: 70808511 | E61: 74088799 | F61: 60693813 | G61: 35917358
B63: 股息分红 | C63: 4.1599127e+08 | D63: 4.0629176e+08 | E63: 322700000 | G63: 276600000 | H63: 138300000
C64: =C54+C33 -> 1.5912889e+10 | D64: =D54+D33 -> 1.3974021e+10 | E64: =E54+E33 -> 1.2057677e+10 | F64: =F54+F33 -> 1.0425669e+10 | G64: =G54+G33 -> 8.5115862e+09 | H64: =H54+H33 -> 6.8439935e+09

Sheet 损益现金流
B1: 2024 | C1: 2023 | D1: 2022 | E1: 2021 | F1: 2020 | G1: 2019
A2: 营收 | B2: 5.1208388e+09 | C2: 4.5559683e+09 | D2: 3.8849595e+09 | E2: 3.2800588e+09 | F2: 2.2609684e+09 | G2: 1.5795206e+09
A3: 营业成本 | B3: 7.6076192e+08 | C3: 6.6984014e+08 | D3: 5.8291066e+08 | E3: 4.2935278e+08 | F3: 2.7813494e+08 | G3: 2.2776573e+08
A4: 毛利率 | B4: =1-B3/B2 -> 0.85143803 | C4: =1-C3/C2 -> 0.85297524 | D4: =1-D3/D2 -> 0.84995708 | E4: =1-E3/E2 -> 0.86910211 | F4: =1-F3/F2 -> 0.87698415 | G4: =1-G3/G2 -> 0.85580072
A5: 税金及附加 | B5: 49170365 | C5: 37161428 | D5: 34743722 | E5: 35179114 | F5: 22921921 | G5: 15936651
A6: 销售费用 | B6: 9.9133253e+08 | C6: 9.6741454e+08 | D6: 8.1820166e+08 | E6: 6.9497017e+08 | F6: 4.8280766e+08 | G6: 3.4473805e+08
A7: 管理费用 | B7: 4.0266289e+08 | C7: 4.4422792e+08 | D7: 3.9190309e+08 | E7: 3.2600319e+08 | F7: 2.1254109e+08 | G7: 1.356965e+08
A8: 研发费用 | B8: 1.6955569e+09 | C8: 1.4722958e+09 | D8: 1.3312108e+09 | E8: 1.081625e+09 | F8: 7.1088189e+08 | G8: 5.9878566e+08
A9: 信用减值 | B9: -15949603 | C9: -16113383 | D9: 2060333.2 | E9: -11630385 | F9: -4182207.5 | G9: -7056972.4
A10: 资产减值 | B10: -8018423.9 | C10: -7155150.3 | D10: -27214231 | E10: -70419.47 | G10: -31084.2
A11: 资产处置 | B11: 181735.73 | C11: 5242488.1 | D11: 160353.87 | E11: 181433.17 | F11: 16587.47 | G11: 2708.67
A12: 其他收益 | B12: 1.7612308e+08 | C12: 1.42203e+08 | D12: 1.7304803e+08 | E12: 1.9860388e+08 | F12: 1.1471942e+08 | G12: 67353894
A13: 营业外收入 | B13: 3918649.7 | C13: 1470784 | D13: 2197939.3 | E13: 3618260.6 | F13: 807603.11
A14: 营业外支出 | B14: -5455007.3 | C14: 12211502 | D14: 517546.52 | E14: 6203330.7 | F14: 318305.79 | G14: -4724895.3
A15: 息税前经营收益 | B15: =B2-B3-SUM(B5:B8)+SUM(B9:B12)+B13-B14 -> 1.3830647e+09 | C15: =C2-C3-SUM(C5:C8)+SUM(C9:C12)+C13-C14 -> 1.0784647e+09 | D15: =D2-D3-SUM(D5:D8)+SUM(D9:D12)+D13-D14 -> 8.7572438e+08 | E15: =E2-E3-SUM(E5:E8)+SUM(E9:E12)+E13-E14 -> 8.9742797e+08 | F15: =F2-F3-SUM(F5:F8)+SUM(F9:F12)+F13-F14 -> 6.6472399e+08 | G15: =G2-G3-SUM(G5:G8)+SUM(G9:G12)+G13-G14 -> 3.2159146e+08
A16: 短期投资收益 | B16: =222158992.8+68762441.84 -> 2.9092143e+08 | C16: =136522034.04+48306921.09 -> 1.8482896e+08 | D16: =189331686.85+77913125.38 -> 2.6724481e+08 | E16: =179922006.63+144658+39731468.87 -> 2.1979813e+08 | F16: =85884376.34+-17907666.67 -> 67976710 | G16: 22832600
A17: 利息收入 | B17: 26432907 | C17: 1.0500676e+08 | D17: 23567706 | E17: 23972438 | F17: 10459654 | G17: 3852556.2
A18: 公允价值变动收益 | B18: =-14547752.34+-3551325.24 -> -18099078 | C18: =6757892.24+-8857233.23 -> -2099341 | D18: =-18984506.87+-5449992.67 -> -24434500 | E18: =-1488669.41+-47825.19 -> -1536494.6 | F18: =115970430.02+2112747.79 -> 1.1808318e+08 | G18: =31977675.53+18277000 -> 50254676
A19: 息税前金融资产收益 | B19: =SUM(B16:B18) -> 2.9925526e+08 | C19: =SUM(C16:C18) -> 2.8773638e+08 | D19: =SUM(D16:D18) -> 2.6637802e+08 | E19: =SUM(E16:E18) -> 2.4223408e+08 | F19: =SUM(F16:F18) -> 1.9651954e+08 | G19: =SUM(G16:G18) -> 76939832
A20: 长期股权收益 | B20: 79011534 | C20: 34333675 | D20: =72734416.41+-735306.57 -> 71999110 | E20: =-14617190.94 -> -14617191 | F20: =-9056226.29+85244610.72 -> 76188384 | G20: 8633041.9
A21: （权益工具）公允价值变动收益 | B21: -288123.06 | C21: -527775.08 | D21: -5276061.5 | E21: 468650.3 | F21: -519287.32 | G21: 41284.67
A22: 长期投资收益 | B22: =SUM(B20:B21) -> 78723411 | C22: =SUM(C20:C21) -> 33805900 | D22: =SUM(D20:D21) -> 66723048 | E22: =SUM(E20:E21) -> -14148541 | F22: =SUM(F20:F21) -> 75669097 | G22: =SUM(G20:G21) -> 8674326.6
A23: 息税前利润总额 | B23: =B15+B19+B22 -> 1.7610434e+09 | C23: =C15+C19+C22 -> 1.4000069e+09 | D23: =D15+D19+D22 -> 1.2088255e+09 | E23: =E15+E19+E22 -> 1.1255135e+09 | F23: =F15+F19+F22 -> 9.3691262e+08 | G23: =G15+G19+G22 -> 4.0720562e+08
A24: 利息支出
A25: 财务费用 | B25: 10620632 | C25: 10167473 | D25: =-(12984610.32-D17) -> 10583095 | E25: =-(17169875.92-E17) -> 6802562.5 | F25: =-(9410173.68-F17) -> 1049480.2 | G25: =-(3018936.31-G17) -> 833619.92
A26: 税前利润总额 | B26: =B23-B25 -> 1.7504227e+09 | C26: =C23-C25 -> 1.3898395e+09 | D26: =D23-D25 -> 1.1982424e+09 | E26: =E23-E25 -> 1.1187109e+09 | F26: =F23-F25 -> 9.3586314e+08 | G26: =G23-G25 -> 4.06372e+08
A27: 所得税 | B27: 95138661 | C27: 75377801 | D27: 67317889 | E27: 49759284 | F27: 49289324 | G27: 5792795.7
A28: 净利润 | B28: =B26-B27 -> 1.6552841e+09 | C28: =C26-C27 -> 1.3144617e+09 | D28: =D26-D27 -> 1.1309245e+09 | E28: =E26-E27 -> 1.0689517e+09 | F28: =F26-F27 -> 8.8657382e+08 | G28: =G26-G27 -> 4.005792e+08
A29: 资产减值准备 | B29: 8018423.9 | C29: 7155150.3 | D29: 27214231 | E29: 70419.47 | G29: 31084.2
A30: 信用减值损失 | B30: 15949603 | C30: 16113383 | D30: -2060333.2 | E30: 11630385 | F30: 4182207.5 | G30: 7056972.4
A31: 资产折旧 | B31: 44432135 | C31: 46721679 | D31: 50377053 | E31: 44287050 | F31: 35723226 | G31: 24893376
A32: 使用权资产折旧 | B32: 42483264 | C32: 44165518 | D32: 46994619 | E32: 27773694
A33: 无形资产摊销 | B33: 19446866 | C33: 24971096 | D33: 25979497 | E33: 20169464 | F33: 9325331.1 | G33: 4511920.1
A34: 长期待摊 | B34: 8489518.3 | C34: 8662878.2 | D34: 6996903.8 | E34: 3309754.1 | F34: 2079507.6 | G34: 2731276.6
A35: 固定资产损失 | B35: -181735.73 | C35: -5242488.1 | D35: -160353.87 | E35: -186023.09 | F35: -16587.47 | G35: -2708.67
A36: 固定资产报废 | C36: -91442 | D36: -21106.11 | F36: 7654.87
A37: 公允价值变动损失 | B37: 18387201 | C37: 2627116.1 | D37: 29710561 | E37: 1067844.3 | F37: -1.1756389e+08 | G37: -50295960
A38: 财务费用 | B38: 8664291.3 | C38: 9274711.4 | D38: 10327234 | E38: 5917385.2 | F38: 773218.68 | G38: 626534.81
A39: 投资损失 | B39: -3.6993297e+08 | C39: -2.1916263e+08 | D39: -3.3924392e+08 | E39: -2.0518094e+08 | F39: -1.4416509e+08 | G39: -31465642
A40: 递延所得税资产减少 | B40: 4344376.5 | C40: -4776914.1 | D40: -2072417.3 | E40: -3274217.8 | F40: -580753.66 | G40: 2040618.8
A41: 递延所得税负债增加 | B41: 8078549.8 | C41: 5525250.9 | D41: 10906417 | E41: 1580367.3 | F41: -5907799.7 | G41: 7270295.2
A42: 存货的减少 | B42: 610750.98 | C42: -233407.07 | D42: 1138738.2 | E42: -948759.37 | F42: 158617.21 | G42: -454444.39
A43: 经营性应收的减少 | B43: 15771283 | C43: -1.0425443e+08 | D43: -1.0799125e+08 | E43: -52507919 | F43: -29063926 | G43: -1.4796119e+08
A44: 经营性应付的增加 | B44: 5.1278956e+08 | C44: 6.9889371e+08 | D44: 5.4536919e+08 | E44: 8.4397949e+08 | F44: 8.1931433e+08 | G44: 3.525246e+08
A45: 其他 | B45: 2.029388e+08 | C45: 2.1273622e+08 | D45: 1.6853525e+08 | E45: 97660817 | F45: 53583869 | G45: 13605559
A46: 经营活动产生现金流净额 | B46: =B28+SUM(B29:B45) -> 2.195574e+09 | C46: =C28+SUM(C29:C45) -> 2.0575471e+09 | D46: =D28+SUM(D29:D45) -> 1.6029248e+09 | E46: =E28+SUM(E29:E45) -> 1.8643005e+09 | F46: =F28+SUM(F29:F45) -> 1.5144237e+09 | G46: =G28+SUM(G29:G45) -> 5.856915e+08
A47: 销售商品、提供劳务收到的现金 | B47: 5.947624e+09 | C47: 5.1439627e+09 | D47: 4.4218604e+09 | E47: 4.1673378e+09 | F47: 2.9363551e+09 | G47: 1.7911457e+09
A48: 收到的税费返还 | B48: 1.0920103e+08 | C48: 89743358 | D48: 1.2215521e+08 | E48: 1.5084418e+08 | F48: 80080764 | G48: 41158516
A49: 收到其他与经营活动有关的现金 | B49: 71943940 | C49: 1.4710194e+08 | D49: 71711813 | E49: 91364660 | F49: 1.1325485e+08 | G49: 72809690
A50: 经营活动现金流入小计 | B50: =SUM(B47:B49) -> 6.128769e+09 | C50: =SUM(C47:C49) -> 5.380808e+09 | D50: =SUM(D47:D49) -> 4.6157274e+09 | E50: =SUM(E47:E49) -> 4.4095467e+09 | F50: =SUM(F47:F49) -> 3.1296907e+09 | G50: =SUM(G47:G49) -> 1.9051139e+09
A51: 购买商品、接受劳务支付的现金 | B51: 1.0631739e+09 | C51: 8.2357086e+08 | D51: 7.058422e+08 | E51: 6.8864635e+08 | F51: 4.8174445e+08 | G51: 4.1305444e+08
A52: 支付给职工以及为职工支付的现金 | B52: 2.2094114e+09 | C52: 1.9661821e+09 | D52: 1.8350235e+09 | E52: 1.3437552e+09 | F52: 8.5805304e+08 | G52: 7.258058e+08
A53: 支付的各项税费 | B53: 4.9642402e+08 | C53: 3.8005899e+08 | D53: 3.7383191e+08 | E53: 4.023956e+08 | F53: 1.7052561e+08 | G53: 1.2227514e+08
A54: 支付其他与经营活动有关的现金 | B54: 1.6418568e+08 | C54: 1.5344893e+08 | D54: 98104963 | E54: 1.1044905e+08 | F54: 1.0494386e+08 | G54: 58287004
A55: 经营活动现金流出小计 | B55: =SUM(B51:B54) -> 3.933195e+09 | C55: =SUM(C51:C54) -> 3.3232609e+09 | D55: =SUM(D51:D54) -> 3.0128026e+09 | E55: =SUM(E51:E54) -> 2.5452462e+09 | F55: =SUM(F51:F54) -> 1.615267e+09 | G55: =SUM(G51:G54) -> 1.3194224e+09
A56: 经营活动产生现金流净额 | B56: =B50-B55 -> 2.195574e+09 | C56: =C50-C55 -> 2.0575471e+09 | D56: =D50-D55 -> 1.6029248e+09 | E56: =E50-E55 -> 1.8643005e+09 | F56: =F50-F55 -> 1.5144237e+09 | G56: =G50-G55 -> 5.856915e+08
A58: 收回投资收到的现金 | B58: 1.2848892e+10 | C58: 9.5226772e+09 | D58: 19612334700 | E58: 13388740000 | F58: 16384717320 | G58: 4546910000
A59: 取得投资收益收到的现金 | B59: 2.6186256e+08 | C59: 1.2681782e+08 | D59: 2.2812022e+08 | E59: 2.0689449e+08 | F59: 1.9768366e+08 | G59: 45212012
A60: 处置固定资产、无形资产和其他长期资产收回的现金净额 | B60: 370986.17 | C60: 312398.62 | D60: 69447.14 | E60: 137561.06 | F60: 188282.97 | G60: 3067.85
A61: 处置子公司及其他营业单位收到的现金净额
A62: 收到其他与投资有关的现金 | D62: 6091176
A63: 投资活动现金流入小计 | B63: =SUM(B58:B62) -> 1.3111125e+10 | C63: =SUM(C58:C62) -> 9.6498074e+09 | D63: =SUM(D58:D62) -> 1.9846616e+10 | E63: =SUM(E58:E62) -> 1.3595772e+10 | F63: =SUM(F58:F62) -> 1.6582589e+10 | G63: =SUM(G58:G62) -> 4.5921251e+09
A64: 购建固定资产、无形资产和其他长期资产支付的现金 | B64: 1.7499178e+08 | C64: 1.6584838e+08 | D64: 1.7596185e+08 | E64: 1.4884581e+08 | F64: 55277441 | G64: 63210239
A65: 投资支付的现金 | B65: 1.7210219e+10 | C65: 1.4693877e+10 | D65: 1.5167917e+10 | E65: 14810832000 | F65: 17495762400 | G65: 9002540000
A66: 支付其他与投资活动有关的现金 | D66: 863547.87 | G66: 1.99
A67: 取得子公司现金 | F67: 1.4786682e+08
A68: 投资活动现金流出小计 | B68: =SUM(B64:B67) -> 1.7385211e+10 | C68: =SUM(C64:C67) -> 1.4859726e+10 | D68: =SUM(D64:D67) -> 1.5344742e+10 | E68: =SUM(E64:E67) -> 1.4959678e+10 | F68: =SUM(F64:F67) -> 1.7698907e+10 | G68: =SUM(G64:G67) -> 9.0657502e+09
A69: 投资活动产生的现金流量净额 | B69: =B63-B68 -> -4.2740851e+09 | C69: =C63-C68 -> -5.2099184e+09 | D69: =D63-D68 -> 4.5018731e+09 | E69: =E63-E68 -> -1.3639058e+09 | F69: =F63-F68 -> -1.1163174e+09 | G69: =G63-G68 -> -4.4736252e+09
A71: 吸收投资收到的现金 | B71: 62051861 | C71: 21919279 | D71: 9871332.2 | G71: 4481541400
A72: 取得借款收到的现金
A73: 收到其他与筹资活动有关的现金 | B73: 2000000 | C73: 2000000 | D73: 1958124 | E73: 52000000 | F73: 2000000
A74: 筹资活动现金流入小计 | B74: =SUM(B71:B73) -> 64051861 | C74: =SUM(C71:C73) -> 23919279 | D74: =SUM(D71:D73) -> 11829456 | E74: =SUM(E71:E73) -> 52000000 | F74: =SUM(F71:F73) -> 2000000 | G74: =SUM(G71:G73) -> 4481541400
A75: 偿还债务支付的现金
A76: 分配股利、利润或偿付利息支付的现金 | B76: 4.0629035e+08 | C76: 3.3672629e+08 | D76: 322700000 | E76: 276600000 | F76: 138300000
A77: 支付其他与筹资活动有关的现金 | B77: 1.5833935e+08 | C77: 71729187 | D77: 43478901 | E77: 22733041 | F77: 5062704 | G77: 32486116
A78: 筹资活动现金流出小计 | B78: =SUM(B75:B77) -> 5.646297e+08 | C78: =SUM(C75:C77) -> 4.0845548e+08 | D78: =SUM(D75:D77) -> 3.661789e+08 | E78: =SUM(E75:E77) -> 2.9933304e+08 | F78: =SUM(F75:F77) -> 143362704 | G78: =SUM(G75:G77) -> 32486116
A79: 筹资活动产生的现金流量净额 | B79: =B74-B78 -> -5.0057784e+08 | C79: =C74-C78 -> -3.845362e+08 | D79: =D74-D78 -> -3.5434944e+08 | E79: =E74-E78 -> -2.4733304e+08 | F79: =F74-F78 -> -141362704 | G79: =G74-G78 -> 4449055284
A83: Net Profit | B83: =B28 -> 1.6552841e+09 | C83: =C28 -> 1.3144617e+09 | D83: =D28 -> 1.1309245e+09 | E83: =E28 -> 1.0689517e+09 | F83: =F28 -> 8.8657382e+08 | G83: =G28 -> 4.005792e+08
A84: Gross Profit | B84: =B2-B3 -> 4.3600769e+09 | C84: =C2-C3 -> 3.8861281e+09 | D84: =D2-D3 -> 3.3020488e+09 | E84: =E2-E3 -> 2.850706e+09 | F84: =F2-F3 -> 1.9828335e+09 | G84: =G2-G3 -> 1.3517549e+09
A85: Revenue | B85: =B2 -> 5.1208388e+09 | C85: =C2 -> 4.5559683e+09 | D85: =D2 -> 3.8849595e+09 | E85: =E2 -> 3.2800588e+09 | F85: =F2 -> 2.2609684e+09 | G85: =G2 -> 1.5795206e+09
A86: FCF | B86: =B56-B64 -> 2.0205822e+09 | C86: =C56-C64 -> 1.8916987e+09 | D86: =D56-D64 -> 1.4269629e+09 | E86: =E56-E64 -> 1.7154547e+09 | F86: =F56-F64 -> 1.4591463e+09 | G86: =G56-G64 -> 5.2248126e+08
A87: TotalShare | B87: =balance!C55 -> 462525643 | C87: =balance!D55 -> 461723327 | D87: =balance!E55 -> 461221529 | E87: =balance!F55 -> 461000000 | F87: =balance!G55 -> 461000000 | G87: =balance!H55 -> 461000000
A88: EPS | B88: =B83/B87 -> 3.5787941 | C88: =C83/C87 -> 2.84686 | D88: =D83/D87 -> 2.4520201 | E88: =E83/E87 -> 2.3187672 | F88: =F83/F87 -> 1.9231536 | G88: =G83/G87 -> 0.86893537
A91: 股东权益（平均） | B91: =(balance!C54+balance!D54)/2 -> 1.0728088e+10 | C91: =(balance!D54+balance!E54)/2 -> 9.4089986e+09 | D91: =(balance!E54+balance!F54)/2 -> 8.2893001e+09 | E91: =(balance!F54+balance!G54)/2 -> 7.3355163e+09 | F91: =(balance!G54+balance!H54)/2 -> 6.4797018e+09
A92: 总资产（平均） | B92: =(balance!C2+balance!D2)/2 -> 1.4943455e+10 | C92: =(balance!D2+balance!E2)/2 -> 1.3015849e+10 | D92: =(balance!E2+balance!F2)/2 -> 1.1241673e+10 | E92: =(balance!F2+balance!G2)/2 -> 9.4686278e+09 | F92: =(balance!G2+balance!H2)/2 -> 7.6777898e+09
A93: ROE | B93: =B83/B91 -> 0.15429442 | C93: =C83/C91 -> 0.13970261 | D93: =D83/D91 -> 0.13643184 | E93: =E83/E91 -> 0.14572276 | F93: =F83/F91 -> 0.13682324
A94: 净利率 | B94: =B83/B85 -> 0.32324471 | C94: =C83/C85 -> 0.28851423 | D94: =D83/D85 -> 0.29110329 | E94: =E83/E85 -> 0.32589406 | F94: =F83/F85 -> 0.39212128
A95: 总资产周转率 | B95: =B85/B92 -> 0.34268105 | C95: =C85/C92 -> 0.35003236 | D95: =D85/D92 -> 0.34558553 | E95: =E85/E92 -> 0.34641332 | F95: =F85/F92 -> 0.29448167
A96: 权益乘数 | B96: =B92/B91 -> 1.3929281 | C96: =C92/C91 -> 1.3833405 | D96: =D92/D91 -> 1.3561667 | E96: =E92/E91 -> 1.2907923 | F96: =F92/F91 -> 1.1848986
A98: 税率 | B98: =B27/B26 -> 0.05435182 | C98: =C27/C26 -> 0.054234897 | D98: =D27/D26 -> 0.056180529 | E98: =E27/E26 -> 0.044479125 | F98: =F27/F26 -> 0.052667235
A99: 业务利润（净） | B99: =B2-B3-SUM(B5:B9) -> 1.2373038e+09 | C99: =C2-C3-SUM(C5:C9) -> 9.8114182e+08 | D99: =D2-D3-SUM(D5:D9) -> 7.2392917e+08 | E99: =E2-E3-SUM(E5:E9) -> 7.2455891e+08 | F99: =F2-F3-SUM(F5:F9) -> 5.578631e+08
A100: 有息债务（平均） | B100: =(balance!C48+balance!D48+balance!C51+balance!D51)/2 -> 95753351 | C100: =(balance!D48+balance!E48+balance!D51+balance!E51)/2 -> 1.0683742e+08 | D100: =(balance!E48+balance!F48+balance!E51+balance!F51)/2 -> 1.2489126e+08 | E100: =(balance!F48+balance!G48+balance!F51+balance!G51)/2 -> 57256601 | F100: =(balance!G48+balance!H48+balance!G51+balance!H51)/2 -> 0
A101: 资本投入 | B101: =B100+B92 -> 1.5039208e+10 | C101: =C100+C92 -> 1.3122686e+10 | D101: =D100+D92 -> 1.1366564e+10 | E101: =E100+E92 -> 9.5258844e+09 | F101: =F100+F92 -> 7.6777898e+09
A102: ROIC | B102: =B99*(1-B98)/B101 -> 0.077800247 | C102: =C99*(1-C98)/C101 -> 0.07071187 | D102: =D99*(1-D98)/D101 -> 0.060111256 | E102: =E99*(1-E98)/E101 -> 0.072678939 | F102: =F99*(1-F98)/F101 -> 0.068832568

Sheet 营运资本变动
A1: 账面余额
B2: 2024.12.31 | C2: 2023.12.31 | D2: 2022.12.31 | E2: 2021.12.31 | F2: 2020.12.31 | G2: 2019.12.31
A3: 应收
A4: 应收票据 | B4: 5309651.7 | C4: 2080000 | D4: 3447750 | E4: 3667000 | F4: 2340900 | G4: 2086153.9
A5: 应收账款 | B5: 5.5627551e+08 | C5: 6.0347318e+08 | D5: 5.1716033e+08 | E5: 4.3820437e+08 | F5: 4.1320446e+08 | G5: 3.5807201e+08
A6: 其他应收款 | B6: 69650288 | C6: 49547645 | D6: 27086472 | E6: 36082150 | F6: 41018315 | G6: 25502706
A7: 合同资产 | B7: 484618.8 | C7: 1922161.3 | D7: 2355541.8 | E7: 2363532.8
A8: 预付款项 | B8: 13981930 | C8: 21957493 | D8: 27596962 | E8: 25601542 | F8: 8383888.8 | G8: 5322052.8
A9: 应收减少 | B9: =SUM(C4:C8)-SUM(B4:B8) -> 33278483 | C9: =SUM(D4:D8)-SUM(C4:C8) -> -1.0133342e+08 | D9: =SUM(E4:E8)-SUM(D4:D8) -> -71728461 | E9: =SUM(F4:F8)-SUM(E4:E8) -> -40971031 | F9: =SUM(G4:G8)-SUM(F4:F8) -> -73964644
A11: 应付
A12: 应付票据
A13: 应付账款 | B13: 4.458657e+08 | C13: 4.5348455e+08 | D13: 3.0630474e+08 | E13: 2.1219664e+08 | F13: 1.4038947e+08 | G13: 60235681
A14: 其他应付款 | B14: 1.1666246e+08 | C14: 1.0367197e+08 | D14: 97531167 | E14: 90666378 | F14: 49333920 | G14: 35618022
A15: 合同负债 | B15: 2.1355359e+09 | C15: 1.8918741e+09 | D15: 1.7312476e+09 | E15: 1.420876e+09 | F15: 8.3275063e+08 | G15: 3.6078418e+08
A16: 应付职工薪酬 | B16: 4.8106591e+08 | C16: 4.6359106e+08 | D16: 3.9433263e+08 | E16: 3.6030722e+08 | F16: 2.4994716e+08 | G16: 1.5529453e+08
A17: 应交税费 | B17: 80085593 | C17: 70268323 | D17: 45606445 | E17: 55460575 | F17: 1.1242866e+08 | G17: 37890686
A18: 其他流动负债 | B18: 1.0721531e+08 | C18: 1.3416301e+08 | D18: 1.0935069e+08 | E18: 88406222 | F18: 52964852 | G18: 18944336
A19: 其他非流动负债 | B19: 9.433486e+08 | C19: 6.058109e+08 | D19: 3.1066637e+08 | E19: 1.6691384e+08 | F19: 84923225 | G19: 57945108
A20: 递延收益 | B20: 2392855.7 | C20: 36640187 | D20: 43847197 | E20: 66634447 | F20: 83720563 | G20: 35553471
A21: 应付增加 | B21: =SUM(B12:B20)-SUM(C12:C20) -> 5.5266818e+08 | C21: =SUM(C12:C20)-SUM(D12:D20) -> 7.206173e+08 | D21: =SUM(D12:D20)-SUM(E12:E20) -> 5.7742551e+08 | E21: =SUM(E12:E20)-SUM(F12:F20) -> 8.5500286e+08 | F21: =SUM(F12:F20)-SUM(G12:G20) -> 8.4419247e+08
A23: 存货 | B23: 977813.13 | C23: 1588564.1 | D23: 1355157 | E23: 2493895.3 | F23: 1545135.9 | G23: 1625294.3
A24: 存货减少 | B24: =C23-B23 -> 610750.98 | C24: =D23-C23 -> -233407.07 | D24: =E23-D23 -> 1138738.2 | E24: =F23-E23 -> -948759.37 | F24: =G23-F23 -> 80158.4

Sheet 收入成本
B1: 2024 | C1: 2023 | D1: 2022 | E1: 2021 | F1: 2020 | G1: 2019 | H1: 2018
A2: 收入
A3: WPS个人业务 | B3: 3.2832925e+09
A4: WPS 365业务 | B4: 4.3650005e+08
A5: WPS 软件业务 | B5: 1.2679458e+09
A6: 其他 | B6: 1.3310043e+08
A8: 国内个人办公服务订阅业务 | C8: 2.6533478e+09 | D8: 2.0501271e+09 | E8: 1.4652985e+09 | F8: 1.1088805e+09 | G8: 6.7952999e+08
A9: 国内机构订阅及服务业务 | C9: 9.5743488e+08 | D9: 691989137 | E9: 4.4626203e+08
A10: 国内机构授权业务 | C10: 6.551452e+08 | D10: 8.3562053e+08 | E10: 9.6244853e+08 | F10: 8.0277615e+08 | G10: 4.0406088e+08
A11: 互联网广告推广服务及其他业务 | C11: 2.9004044e+08 | D11: 3.0644795e+08 | E11: 4.0560205e+08 | F11: 3.490788e+08 | G11: 4.9584121e+08
A13: 成本
A14: WPS个人业务 | B14: 6.1743714e+08
A15: WPS 365业务 | B15: 38597698
A16: WPS 软件业务 | B16: 92285167
A17: 其他 | B17: 12441908
A19: 国内个人办公服务订阅业务 | C19: 4.9102611e+08 | D19: 3.9465899e+08 | E19: 2.5211766e+08 | F19: 1.6950594e+08 | G19: 1.30922e+08
A20: 国内机构订阅及服务业务 | C20: 69896550 | D20: 45732607 | E20: 22910359
A21: 国内机构授权业务 | C21: 45043823 | D21: 54917864 | E21: 38139386 | F21: 31581106 | G21: 84207292
A22: 互联网广告推广服务及其他业务 | C22: 63873653 | D22: 86963741 | E22: 1.1573906e+08 | F22: 76811386 | G22: 12541145
A24: 主营业务收入 | B24: 5.119463e+09 | C24: 4.5538495e+09 | D24: 3.8841847e+09 | E24: 3.2796111e+09 | F24: 2.2607354e+09 | G24: 1.5794321e+09 | H24: 1.1295442e+09
A25: 主营业务成本 | B25: 7.5978507e+08 | C25: 6.6878086e+08 | D25: 5.822732e+08 | E25: 4.2890647e+08 | F25: 2.7789843e+08 | G25: 2.2767043e+08 | H25: 1.4997763e+08
A26: 主营业务毛利 | B26: =B24-B25 -> 4.3596779e+09 | C26: =C24-C25 -> 3.8850687e+09 | D26: =D24-D25 -> 3.3019115e+09 | E26: =E24-E25 -> 2.8507046e+09 | F26: =F24-F25 -> 1.982837e+09 | G26: =G24-G25 -> 1.3517616e+09 | H26: =H24-H25 -> 9.795666e+08
A27: 毛利率 | B27: =B26/B24 -> 0.85158891 | C27: =C26/C24 -> 0.85313945 | D27: =D26/D24 -> 0.85009127 | E27: =E26/E24 -> 0.86922033 | F27: =F26/F24 -> 0.87707609 | G27: =G26/G24 -> 0.85585298 | H27: =H26/H24 -> 0.86722288
A28: 其他业务收入 | B28: 1375821.2 | C28: 2118764.9 | D28: 774759.28 | E28: 447652.85 | F28: 232986.85 | G28: 88531.37 | H28: 136912.34
A29: 其他业务成本 | B29: 976847.73 | C29: 1059280 | D29: 637454.61 | E29: 446317.47 | F29: 236511.47 | G29: 95300 | H29: 136250
A30: 其他业务毛利 | B30: =B28-B29 -> 398973.52 | C30: =C28-C29 -> 1059484.9 | D30: =D28-D29 -> 137304.67 | E30: =E28-E29 -> 1335.38 | F30: =F28-F29 -> -3524.62 | G30: =G28-G29 -> -6768.63 | H30: =H28-H29 -> 662.34
A31: 毛利率 | B31: =B30/B28 -> 0.28998936 | C31: =C30/C28 -> 0.50004836 | D31: =D30/D28 -> 0.17722236 | E31: =E30/E28 -> 0.0029830705 | F31: =F30/F28 -> -0.015127978 | G31: =G30/G28 -> -0.076454595 | H31: =H30/H28 -> 0.004837694

Sheet Beta_04
B1: 定价 | C1: 定价 | D1: 2024 | E1: 2023 | F1: 2022 | G1: 2021 | H1: 2020 | I1: 2019
A2: 资产 | D2: ='balance sheet（处理后）'!C2 -> 1.5912889e+10 | E2: ='balance sheet（处理后）'!D2 -> 1.3974021e+10 | F2: ='balance sheet（处理后）'!E2 -> 1.2057677e+10 | G2: ='balance sheet（处理后）'!F2 -> 1.0425669e+10 | H2: ='balance sheet（处理后）'!G2 -> 8.5115862e+09 | I2: ='balance sheet（处理后）'!H2 -> 6.8439935e+09
A3: 现金 | D3: ='balance sheet（处理后）'!C3 -> 1.2812479e+10 | E3: ='balance sheet（处理后）'!D3 -> 1.1392118e+10 | F3: ='balance sheet（处理后）'!E3 -> 1.0293767e+10 | G3: ='balance sheet（处理后）'!F3 -> 9.2193082e+09 | H3: ='balance sheet（处理后）'!G3 -> 7.6442103e+09 | I3: ='balance sheet（处理后）'!H3 -> 6.2955176e+09
A4: 投资 | D4: ='balance sheet（处理后）'!C10 -> 1.5837826e+09 | E4: ='balance sheet（处理后）'!D10 -> 1.1148938e+09 | F4: ='balance sheet（处理后）'!E10 -> 4.913314e+08 | G4: ='balance sheet（处理后）'!F10 -> 1.6841795e+08 | H4: ='balance sheet（处理后）'!G10 -> 53083238 | I4: ='balance sheet（处理后）'!H10 -> 38612671
A5: 运营资产 | D5: ='balance sheet（处理后）'!C15 -> 7.2816093e+08 | E5: ='balance sheet（处理后）'!D15 -> 7.6115434e+08 | F5: ='balance sheet（处理后）'!E15 -> 647433732 | G5: ='balance sheet（处理后）'!F15 -> 5.3505509e+08 | H5: ='balance sheet（处理后）'!G15 -> 4.961692e+08 | I5: ='balance sheet（处理后）'!H15 -> 4.1410836e+08
A6: 应收 | D6: ='balance sheet（处理后）'!C16+'balance sheet（处理后）'!C17 -> 5.0987671e+08 | E6: ='balance sheet（处理后）'!D16+'balance sheet（处理后）'!D17 -> 5.6902035e+08 | F6: ='balance sheet（处理后）'!E16+'balance sheet（处理后）'!E17 -> 5.0023927e+08 | G6: ='balance sheet（处理后）'!F16+'balance sheet（处理后）'!F17 -> 4.1519832e+08 | H6: ='balance sheet（处理后）'!G16+'balance sheet（处理后）'!G17 -> 4.0044938e+08 | I6: ='balance sheet（处理后）'!H16+'balance sheet（处理后）'!H17 -> 3.4710952e+08
A7: 预付 | D7: =balance!C18 -> 13981930 | E7: =balance!D18 -> 21957493 | F7: =balance!E18 -> 27596962 | G7: =balance!F18 -> 25601542 | H7: =balance!G18 -> 8383888.8 | I7: =balance!H18 -> 5322052.8
A8: 存货 | D8: ='balance sheet（处理后）'!C20 -> 802036.62 | E8: ='balance sheet（处理后）'!D20 -> 1412787.6 | F8: ='balance sheet（处理后）'!E20 -> 1157966.9 | G8: ='balance sheet（处理后）'!F20 -> 2296705.1 | H8: ='balance sheet（处理后）'!G20 -> 1347945.7 | I8: ='balance sheet（处理后）'!H20 -> 1428104.1
A9: 长期资产 | D9: ='balance sheet（处理后）'!C26 -> 7.8846634e+08 | E9: ='balance sheet（处理后）'!D26 -> 7.0585543e+08 | F9: ='balance sheet（处理后）'!E26 -> 6.2514484e+08 | G9: ='balance sheet（处理后）'!F26 -> 5.0288813e+08 | H9: ='balance sheet（处理后）'!G26 -> 3.1812341e+08 | I9: ='balance sheet（处理后）'!H26 -> 95754892
A10: 负债 | D10: ='balance sheet（处理后）'!C34 -> 4.4763191e+09 | E10: ='balance sheet（处理后）'!D34 -> 3.9544151e+09 | F10: ='balance sheet（处理后）'!E34 -> 3.2592856e+09 | G10: ='balance sheet（处理后）'!F34 -> 2.6454601e+09 | H10: ='balance sheet（处理后）'!G34 -> 1.6207629e+09 | I10: ='balance sheet（处理后）'!H34 -> 7.7541323e+08
A11: 预收 | D11: ='balance sheet（处理后）'!C38+'balance sheet（处理后）'!C46 -> 3.0788845e+09 | E11: ='balance sheet（处理后）'!D38+'balance sheet（处理后）'!D46 -> 2.504513e+09 | F11: ='balance sheet（处理后）'!E38+'balance sheet（处理后）'!E46 -> 2.048529e+09 | G11: ='balance sheet（处理后）'!F38+'balance sheet（处理后）'!F46 -> 1.5942159e+09 | H11: ='balance sheet（处理后）'!G38+'balance sheet（处理后）'!G46 -> 9.1767385e+08 | I11: ='balance sheet（处理后）'!H38+'balance sheet（处理后）'!H46 -> 0
A12: 应付 | D12: ='balance sheet（处理后）'!C36 -> 4.458657e+08 | E12: ='balance sheet（处理后）'!D36 -> 4.5348455e+08 | F12: ='balance sheet（处理后）'!E36 -> 3.0630474e+08 | G12: ='balance sheet（处理后）'!F36 -> 2.1219664e+08 | H12: ='balance sheet（处理后）'!G36 -> 1.4038947e+08 | I12: ='balance sheet（处理后）'!H36 -> 60235681
A13: 有息负债 | D13: ='balance sheet（处理后）'!C49+'balance sheet（处理后）'!C52 -> 1.1310118e+08 | E13: ='balance sheet（处理后）'!D49+'balance sheet（处理后）'!D52 -> 78405526 | F13: ='balance sheet（处理后）'!E49+'balance sheet（处理后）'!E52 -> 1.3526932e+08 | G13: ='balance sheet（处理后）'!F49+'balance sheet（处理后）'!F52 -> 1.145132e+08 | H13: ='balance sheet（处理后）'!G49+'balance sheet（处理后）'!G52 -> 0 | I13: ='balance sheet（处理后）'!H49+'balance sheet（处理后）'!H52 -> 0
A14: 权益 | D14: ='balance sheet（处理后）'!C55 -> 1.143657e+10 | E14: ='balance sheet（处理后）'!D55 -> 1.0019606e+10 | F14: ='balance sheet（处理后）'!E55 -> 8.798391e+09 | G14: ='balance sheet（处理后）'!F55 -> 7.7802093e+09 | H14: ='balance sheet（处理后）'!G55 -> 6.8908233e+09 | I14: ='balance sheet（处理后）'!H55 -> 6.0685803e+09
A15: 资本投入 | D15: ='balance sheet（处理后）'!C56+'balance sheet（处理后）'!C57+'balance sheet（处理后）'!C58 -> 5.8032875e+09 | E15: ='balance sheet（处理后）'!D56+'balance sheet（处理后）'!D57+'balance sheet（处理后）'!D58 -> 5.6395207e+09 | F15: ='balance sheet（处理后）'!E56+'balance sheet（处理后）'!E57+'balance sheet（处理后）'!E58 -> 5.4028629e+09 | G15: ='balance sheet（处理后）'!F56+'balance sheet（处理后）'!F57+'balance sheet（处理后）'!F58 -> 5.2085227e+09 | H15: ='balance sheet（处理后）'!G56+'balance sheet（处理后）'!G57+'balance sheet（处理后）'!G58 -> 5.1029105e+09 | I15: ='balance sheet（处理后）'!H56+'balance sheet（处理后）'!H57+'balance sheet（处理后）'!H58 -> 5.0492526e+09
A16: 未分配利润 | D16: ='balance sheet（处理后）'!C61 -> 5.3013467e+09 | E16: ='balance sheet（处理后）'!D61 -> 4.0930628e+09 | F16: ='balance sheet（处理后）'!E61 -> 3.1570626e+09 | G16: ='balance sheet（处理后）'!F61 -> 2.4081747e+09 | H16: ='balance sheet（处理后）'!G61 -> 1.6808484e+09 | I16: ='balance sheet（处理后）'!H61 -> 9.5315356e+08
A17: 股息分红 | D17: =balance!C63 -> 4.1599127e+08 | E17: =balance!D63 -> 4.0629176e+08 | F17: =balance!E63 -> 322700000 | G17: =balance!F63 -> 0 | H17: =balance!G63 -> 276600000 | I17: =balance!H63 -> 138300000
A19: 现金结构
A20: 利润留存 | D20: =D16 -> 5.3013467e+09 | E20: =E16 -> 4.0930628e+09 | F20: =F16 -> 3.1570626e+09 | G20: =G16 -> 2.4081747e+09 | H20: =H16 -> 1.6808484e+09 | I20: =I16 -> 9.5315356e+08
A21: 股东、负债 | D21: =D3-D20 -> 7.5111322e+09 | E21: =E3-E20 -> 7.2990549e+09 | F21: =F3-F20 -> 7.136704e+09 | G21: =G3-G20 -> 6.8111335e+09 | H21: =H3-H20 -> 5.9633619e+09 | I21: =I3-I20 -> 5.342364e+09
A23: 折旧摊销 | D23: =SUM(损益现金流!B29:B34) -> 1.3881981e+08 | E23: =SUM(损益现金流!C29:C34) -> 1.4778971e+08 | F23: =SUM(损益现金流!D29:D34) -> 1.5550197e+08 | G23: =SUM(损益现金流!E29:E34) -> 1.0724077e+08 | H23: =SUM(损益现金流!F29:F34) -> 51310272 | I23: =SUM(损益现金流!G29:G34) -> 39224630
A24: 资本开支 | D24: =损益现金流!B64 -> 1.7499178e+08 | E24: =损益现金流!C64 -> 1.6584838e+08 | F24: =损益现金流!D64 -> 1.7596185e+08 | G24: =损益现金流!E64 -> 1.4884581e+08 | H24: =损益现金流!F64 -> 55277441 | I24: =损益现金流!G64 -> 63210239
A26: 股本 | B26: =C26 -> 462525643 | C26: =D26 -> 462525643 | D26: ='balance sheet（处理后）'!C56 -> 462525643 | E26: ='balance sheet（处理后）'!D56 -> 461723327 | F26: ='balance sheet（处理后）'!E56 -> 461221529 | G26: ='balance sheet（处理后）'!F56 -> 461000000 | H26: ='balance sheet（处理后）'!G56 -> 461000000 | I26: ='balance sheet（处理后）'!H56 -> 461000000
A28: 主营收入 | D28: =收入成本!B24 -> 5.119463e+09 | E28: =收入成本!C24 -> 4.5538495e+09 | F28: =收入成本!D24 -> 3.8841847e+09 | G28: =收入成本!E24 -> 3.2796111e+09 | H28: =收入成本!F24 -> 2.2607354e+09 | I28: =收入成本!G24 -> 1.5794321e+09
A29: 主营成本 | D29: =收入成本!B25 -> 7.5978507e+08 | E29: =收入成本!C25 -> 6.6878086e+08 | F29: =收入成本!D25 -> 5.822732e+08 | G29: =收入成本!E25 -> 4.2890647e+08 | H29: =收入成本!F25 -> 2.7789843e+08 | I29: =收入成本!G25 -> 2.2767043e+08
A30: 费用 | D30: =SUM(损益现金流!B5:B8) -> 3.1387226e+09 | E30: =SUM(损益现金流!C5:C8) -> 2.9210997e+09 | F30: =SUM(损益现金流!D5:D8) -> 2.5760593e+09 | G30: =SUM(损益现金流!E5:E8) -> 2.1377774e+09 | H30: =SUM(损益现金流!F5:F8) -> 1.4291526e+09 | I30: =SUM(损益现金流!G5:G8) -> 1.0951569e+09
A31: 研发费用 | D31: =损益现金流!B8 -> 1.6955569e+09 | E31: =损益现金流!C8 -> 1.4722958e+09 | F31: =损益现金流!D8 -> 1.3312108e+09 | G31: =损益现金流!E8 -> 1.081625e+09 | H31: =损益现金流!F8 -> 7.1088189e+08 | I31: =损益现金流!G8 -> 5.9878566e+08
A32: 销售费用 | D32: =损益现金流!B6 -> 9.9133253e+08 | E32: =损益现金流!C6 -> 9.6741454e+08 | F32: =损益现金流!D6 -> 8.1820166e+08 | G32: =损益现金流!E6 -> 6.9497017e+08 | H32: =损益现金流!F6 -> 4.8280766e+08 | I32: =损益现金流!G6 -> 3.4473805e+08
A33: 管理费用 | D33: =损益现金流!B7 -> 4.0266289e+08 | E33: =损益现金流!C7 -> 4.4422792e+08 | F33: =损益现金流!D7 -> 3.9190309e+08 | G33: =损益现金流!E7 -> 3.2600319e+08 | H33: =损益现金流!F7 -> 2.1254109e+08 | I33: =损益现金流!G7 -> 1.356965e+08
A34: 损耗 | D34: =SUM(损益现金流!B9:B11) -> -23786292 | E34: =SUM(损益现金流!C9:C11) -> -18026045 | F34: =SUM(损益现金流!D9:D11) -> -24993544 | G34: =SUM(损益现金流!E9:E11) -> -11519371 | H34: =SUM(损益现金流!F9:F11) -> -4165620 | I34: =SUM(损益现金流!G9:G11) -> -7085348
A35: 其他收益 | D35: =损益现金流!B12 -> 1.7612308e+08 | E35: =损益现金流!C12 -> 1.42203e+08 | F35: =损益现金流!D12 -> 1.7304803e+08 | G35: =损益现金流!E12 -> 1.9860388e+08 | H35: =损益现金流!F12 -> 1.1471942e+08 | I35: =损益现金流!G12 -> 67353894
A36: 现金收益 | D36: =损益现金流!B19 -> 2.9925526e+08 | E36: =损益现金流!C19 -> 2.8773638e+08 | F36: =损益现金流!D19 -> 2.6637802e+08 | G36: =损益现金流!E19 -> 2.4223408e+08 | H36: =损益现金流!F19 -> 1.9651954e+08 | I36: =损益现金流!G19 -> 76939832
A37: 股权收益 | D37: =损益现金流!B22 -> 78723411 | E37: =损益现金流!C22 -> 33805900 | F37: =损益现金流!D22 -> 66723048 | G37: =损益现金流!E22 -> -14148541 | H37: =损益现金流!F22 -> 75669097 | I37: =损益现金流!G22 -> 8674326.6
A38: 利息支出 | D38: =损益现金流!B24 -> 0 | E38: =损益现金流!C24 -> 0 | F38: =损益现金流!D24 -> 0 | G38: =损益现金流!E24 -> 0 | H38: =损益现金流!F24 -> 0 | I38: =损益现金流!G24 -> 0
A39: 财务费用 | D39: =损益现金流!B25 -> 10620632 | E39: =损益现金流!C25 -> 10167473 | F39: =损益现金流!D25 -> 10583095 | G39: =损益现金流!E25 -> 6802562.5 | H39: =损益现金流!F25 -> 1049480.2 | I39: =损益现金流!G25 -> 833619.92
A40: 其他业务
A41: 收入 | D41: =收入成本!B28 -> 1375821.2 | E41: =收入成本!C28 -> 2118764.9 | F41: =收入成本!D28 -> 774759.28 | G41: =收入成本!E28 -> 447652.85 | H41: =收入成本!F28 -> 232986.85 | I41: =收入成本!G28 -> 88531.37
A42: 成本 | D42: =收入成本!B29 -> 976847.73 | E42: =收入成本!C29 -> 1059280 | F42: =收入成本!D29 -> 637454.61 | G42: =收入成本!E29 -> 446317.47 | H42: =收入成本!F29 -> 236511.47 | I42: =收入成本!G29 -> 95300
A43: 营业外
A44: 收入 | D44: =损益现金流!B13 -> 3918649.7 | E44: =损益现金流!C13 -> 1470784 | F44: =损益现金流!D13 -> 2197939.3 | G44: =损益现金流!E13 -> 3618260.6 | H44: =损益现金流!F13 -> 807603.11 | I44: =损益现金流!G13 -> 0
A45: 成本 | D45: =损益现金流!B14 -> -5455007.3 | E45: =损益现金流!C14 -> 12211502 | F45: =损益现金流!D14 -> 517546.52 | G45: =损益现金流!E14 -> 6203330.7 | H45: =损益现金流!F14 -> 318305.79 | I45: =损益现金流!G14 -> -4724895.3
A46: 所得税 | D46: =损益现金流!B27 -> 95138661 | E46: =损益现金流!C27 -> 75377801 | F46: =损益现金流!D27 -> 67317889 | G46: =损益现金流!E27 -> 49759284 | H46: =损益现金流!F27 -> 49289324 | I46: =损益现金流!G27 -> 5792795.7
A49: 盈利结构
A50: 主营收入 | D50: =D28 -> 5.119463e+09 | E50: =E28 -> 4.5538495e+09 | F50: =F28 -> 3.8841847e+09 | G50: =G28 -> 3.2796111e+09 | H50: =H28 -> 2.2607354e+09 | I50: =I28 -> 1.5794321e+09
A51: 主营成本 | D51: =D29 -> 7.5978507e+08 | E51: =E29 -> 6.6878086e+08 | F51: =F29 -> 5.822732e+08 | G51: =G29 -> 4.2890647e+08 | H51: =H29 -> 2.7789843e+08 | I51: =I29 -> 2.2767043e+08
A52: 费用 | D52: =D30 -> 3.1387226e+09 | E52: =E30 -> 2.9210997e+09 | F52: =F30 -> 2.5760593e+09 | G52: =G30 -> 2.1377774e+09 | H52: =H30 -> 1.4291526e+09 | I52: =I30 -> 1.0951569e+09
A53: 损耗 | D53: =D34 -> -23786292 | E53: =E34 -> -18026045 | F53: =F34 -> -24993544 | G53: =G34 -> -11519371 | H53: =H34 -> -4165620 | I53: =I34 -> -7085348
A54: 其他收益 | D54: =D35 -> 1.7612308e+08 | E54: =E35 -> 1.42203e+08 | F54: =F35 -> 1.7304803e+08 | G54: =G35 -> 1.9860388e+08 | H54: =H35 -> 1.1471942e+08 | I54: =I35 -> 67353894
A55: 现金收益 | D55: =D36 -> 2.9925526e+08 | E55: =E36 -> 2.8773638e+08 | F55: =F36 -> 2.6637802e+08 | G55: =G36 -> 2.4223408e+08 | H55: =H36 -> 1.9651954e+08 | I55: =I36 -> 76939832
A56: 利息支出 | D56: =D38 -> 0 | E56: =E38 -> 0 | F56: =F38 -> 0 | G56: =G38 -> 0 | H56: =H38 -> 0 | I56: =I38 -> 0
A57: 财务费用 | D57: =D39 -> 10620632 | E57: =E39 -> 10167473 | F57: =F39 -> 10583095 | G57: =G39 -> 6802562.5 | H57: =H39 -> 1049480.2 | I57: =I39 -> 833619.92
A58: 所得税 | D58: =D46 -> 95138661 | E58: =E46 -> 75377801 | F58: =F46 -> 67317889 | G58: =G46 -> 49759284 | H58: =H46 -> 49289324 | I58: =I46 -> 5792795.7
A59: 业务利润 | B59: =D59*1.3 -> 2.0368244e+09 | C59: =D59 -> 1.566788e+09 | D59: =D50-D51-D52+D53+D54+D55-D56-D57-D58 -> 1.566788e+09 | E59: =E50-E51-E52+E53+E54+E55-E56-E57-E58 -> 1.290337e+09 | F59: =F50-F51-F52+F53+F54+F55-F56-F57-F58 -> 1.0623837e+09 | G59: =G50-G51-G52+G53+G54+G55-G56-G57-G58 -> 1.0856839e+09 | H59: =H50-H51-H52+H53+H54+H55-H56-H57-H58 -> 8.1041895e+08 | I59: =I50-I51-I52+I53+I54+I55-I56-I57-I58 -> 3.8718675e+08
A60: 股权收益 | D60: =D37 -> 78723411 | E60: =E37 -> 33805900 | F60: =F37 -> 66723048 | G60: =G37 -> -14148541 | H60: =H37 -> 75669097 | I60: =I37 -> 8674326.6
A61: 其他业务利润 | D61: =D41-D42 -> 398973.52 | E61: =E41-E42 -> 1059484.9 | F61: =F41-F42 -> 137304.67 | G61: =G41-G42 -> 1335.38 | H61: =H41-H42 -> -3524.62 | I61: =I41-I42 -> -6768.63
A62: 营业外利润 | D62: =D44-D45 -> 9373657 | E62: =E44-E45 -> -10740718 | F62: =F44-F45 -> 1680392.8 | G62: =G44-G45 -> -2585070.1 | H62: =H44-H45 -> 489297.32 | I62: =I44-I45 -> 4724895.3
A63: 净利润 | D63: =SUM(D59:D62) -> 1.6552841e+09 | E63: =SUM(E59:E62) -> 1.3144617e+09 | F63: =SUM(F59:F62) -> 1.1309245e+09 | G63: =SUM(G59:G62) -> 1.0689517e+09 | H63: =SUM(H59:H62) -> 8.8657382e+08 | I63: =SUM(I59:I62) -> 4.005792e+08
A64: 分红 | D64: =D17 -> 4.1599127e+08 | E64: =E17 -> 4.0629176e+08 | F64: =F17 -> 322700000 | G64: =G17 -> 0 | H64: =H17 -> 276600000 | I64: =I17 -> 138300000
A65: 利润留存 | D65: =D63-D64 -> 1.2392928e+09 | E65: =E63-E64 -> 9.0816992e+08 | F65: =F63-F64 -> 8.0822447e+08 | G65: =G63-G64 -> 1.0689517e+09 | H65: =H63-H64 -> 6.0997382e+08 | I65: =I63-I64 -> 2.622792e+08
A66: 折旧摊销 | D66: =D23 -> 1.3881981e+08 | E66: =E23 -> 1.4778971e+08 | F66: =F23 -> 1.5550197e+08 | G66: =G23 -> 1.0724077e+08 | H66: =H23 -> 51310272 | I66: =I23 -> 39224630
A67: CAPEX | D67: =D24 -> 1.7499178e+08 | E67: =E24 -> 1.6584838e+08 | F67: =F24 -> 1.7596185e+08 | G67: =G24 -> 1.4884581e+08 | H67: =H24 -> 55277441 | I67: =I24 -> 63210239
A68: 现金留存 | D68: =D65+D66-D67 -> 1.2031208e+09 | E68: =E65+E66-E67 -> 8.9011125e+08 | F68: =F65+F66-F67 -> 7.8776459e+08 | G68: =G65+G66-G67 -> 1.0273466e+09 | H68: =H65+H66-H67 -> 6.0600665e+08 | I68: =I65+I66-I67 -> 2.382936e+08
A69: 业务现金 | D69: =D63+D66-D67 -> 1.6191121e+09 | E69: =E63+E66-E67 -> 1.296403e+09 | F69: =F63+F66-F67 -> 1.1104646e+09 | G69: =G63+G66-G67 -> 1.0273466e+09 | H69: =H63+H66-H67 -> 8.8260665e+08 | I69: =I63+I66-I67 -> 3.765936e+08
A71: 经营周转
A72: 毛利率 | D72: =1-D29/D28 -> 0.85158891 | E72: =1-E29/E28 -> 0.85313945 | F72: =1-F29/F28 -> 0.85009127 | G72: =1-G29/G28 -> 0.86922033 | H72: =1-H29/H28 -> 0.87707609 | I72: =1-I29/I28 -> 0.85585298
A73: 费率 | D73: =D30/D28 -> 0.61309607 | E73: =E30/E28 -> 0.64145723 | F73: =F30/F28 -> 0.66321751 | G73: =G30/G28 -> 0.6518387 | H73: =H30/H28 -> 0.63216268 | I73: =I30/I28 -> 0.69338648
A74: 研发费率 | D74: =D31/D28 -> 0.33119819 | E74: =E31/E28 -> 0.32330796 | F74: =F31/F28 -> 0.34272593 | G74: =G31/G28 -> 0.32980281 | H74: =H31/H28 -> 0.31444719 | I74: =I31/I28 -> 0.37911454
A75: 销售费率 | D75: =D32/D28 -> 0.19363995 | E75: =E32/E28 -> 0.21243885 | F75: =F32/F28 -> 0.21064952 | G75: =G32/G28 -> 0.21190628 | H75: =H32/H28 -> 0.21356221 | I75: =I32/I28 -> 0.21826709
A76: 管理费率 | D76: =D33/D28 -> 0.078653345 | E76: =E33/E28 -> 0.097549979 | F76: =F33/F28 -> 0.10089713 | G76: =G33/G28 -> 0.099403002 | H76: =H33/H28 -> 0.094014138 | I76: =I33/I28 -> 0.08591474
A77: 净利率 | D77: =D59/D28 -> 0.30604539 | E77: =E59/E28 -> 0.28335082 | F77: =F59/F28 -> 0.27351524 | G77: =G59/G28 -> 0.33104045 | H77: =H59/H28 -> 0.35847581 | I77: =I59/I28 -> 0.24514302
A79: 应收占比 | D79: =D6/D28 -> 0.099595742 | E79: =E6/E28 -> 0.1249537 | F79: =F6/F28 -> 0.12878874 | G79: =G6/G28 -> 0.12659987 | H79: =H6/H28 -> 0.17713235 | I79: =I6/I28 -> 0.21976856
A80: 应收周转 | D80: =D28/D6 -> 10.04059 | E80: =E28/E6 -> 8.0029643 | F80: =F28/F6 -> 7.7646538 | G80: =G28/G6 -> 7.8989025 | H80: =H28/H6 -> 5.6454961 | I80: =I28/I6 -> 4.5502414
A81: 存货周转 | D81: =D29/D8 -> 947.31967 | E81: =E29/E8 -> 473.37679 | F81: =F29/F8 -> 502.84099 | G81: =G29/G8 -> 186.7486 | H81: =H29/H8 -> 206.1644 | I81: =I29/I8 -> 159.42145
A82: 应付（预付）占比 | D82: =(D12-D7)/D29 -> 0.56842886 | E82: =(E12-E7)/E29 -> 0.64524434 | F82: =(F12-F7)/F29 -> 0.47865466 | G82: =(G12-G7)/G29 -> 0.43504846 | H82: =(H12-H7)/H29 -> 0.47501376 | I82: =(I12-I7)/I29 -> 0.24119789
A83: 预收占比 | D83: =D11/D28 -> 0.60140771 | E83: =E11/E28 -> 0.54997712 | F83: =F11/F28 -> 0.52740256 | G83: =G11/G28 -> 0.48609905 | H83: =H11/H28 -> 0.40591829 | I83: =I11/I28 -> 0
A84: 利息支出/业务利润 | D84: =D56/D59 -> 0 | E84: =E56/E59 -> 0 | F84: =F56/F59 -> 0 | G84: =G56/G59 -> 0 | H84: =H56/H59 -> 0 | I84: =I56/I59 -> 0
A85: 折旧摊销/长期资产 | D85: =D23/D9 -> 0.17606308 | E85: =E23/E9 -> 0.20937673 | F85: =F23/F9 -> 0.24874551 | G85: =G23/G9 -> 0.21324975 | H85: =H23/H9 -> 0.16129046 | I85: =I23/I9 -> 0.40963578
A87: 资产结构
A88: 现金资产 | D88: =D3/D2 -> 0.80516361 | E88: =E3/E2 -> 0.81523546 | F88: =F3/F2 -> 0.85371062 | G88: =G3/G2 -> 0.88428933 | H88: =H3/H2 -> 0.89809469 | I88: =I3/I2 -> 0.91986025
A89: 股权资产 | D89: =D4/D2 -> 0.099528289 | E89: =E4/E2 -> 0.079783318 | F89: =F4/F2 -> 0.040748431 | G89: =G4/G2 -> 0.016154162 | H89: =H4/H2 -> 0.0062365859 | I89: =I4/I2 -> 0.0056418333
A90: 经营资产 | D90: =D5/D2 -> 0.045759192 | E90: =E5/E2 -> 0.054469241 | F90: =F5/F2 -> 0.053694734 | G90: =G5/G2 -> 0.051320934 | H90: =H5/H2 -> 0.058293388 | I90: =I5/I2 -> 0.060506831
A91: 长期资产 | D91: =D9/D2 -> 0.049548913 | E91: =E9/E2 -> 0.050511976 | F91: =F9/F2 -> 0.051846211 | G91: =G9/G2 -> 0.048235572 | H91: =H9/H2 -> 0.037375338 | I91: =I9/I2 -> 0.013991085
A92: 负债结构
A93: 经营负债 | D93: =(D10-D13)/D2 -> 0.27419396 | E93: =(E10-E13)/E2 -> 0.27737252 | F93: =(F10-F13)/F2 -> 0.25908941 | G93: =(G10-G13)/G2 -> 0.24276109 | H93: =(H10-H13)/H2 -> 0.19041843 | I93: =(I10-I13)/I2 -> 0.11329836
A94: 有息负债 | D94: =D13/D2 -> 0.00710752 | E94: =E13/E2 -> 0.0056108063 | F94: =F13/F2 -> 0.011218522 | G94: =G13/G2 -> 0.010983774 | H94: =H13/H2 -> 0 | I94: =I13/I2 -> 0
A95: 权益结构
A96: 资本投入 | D96: =D15/D2 -> 0.36469101 | E96: =E15/E2 -> 0.40357178 | F96: =F15/F2 -> 0.44808491 | G96: =G15/G2 -> 0.49958641 | H96: =H15/H2 -> 0.59952521 | I96: =I15/I2 -> 0.73776408
A97: 利润留存 | D97: =D16/D2 -> 0.33314798 | E97: =E16/E2 -> 0.29290515 | F97: =F16/F2 -> 0.26183009 | G97: =G16/G2 -> 0.23098514 | H97: =H16/H2 -> 0.19747769 | I97: =I16/I2 -> 0.13926862
A99: 营收YoY | D99: =D28/E28-1 -> 0.12420557 | E99: =E28/F28-1 -> 0.17240807 | F99: =F28/G28-1 -> 0.18434308 | G99: =G28/H28-1 -> 0.4506833 | H99: =H28/I28-1 -> 0.43135969
A100: 业务净利润YoY | D100: =D63/E63-1 -> 0.25928667 | E100: =E63/F63-1 -> 0.16228953 | F100: =F63/G63-1 -> 0.057975311 | G100: =G63/H63-1 -> 0.20571084 | H100: =H63/I63-1 -> 1.2132298
A102: 资产YoY | D102: =D2/E2-1 -> 0.138748 | E102: =E2/F2-1 -> 0.15893151 | F102: =F2/G2-1 -> 0.1565374 | G102: =G2/H2-1 -> 0.22487973 | H102: =H2/I2-1 -> 0.24365784
A103: 现金 | D103: =(D3-E3)/(D2-E2)*D102 -> 0.10164298 | E103: =(E3-F3)/(E2-F2)*E102 -> 0.091091441 | F103: =(F3-G3)/(F2-G2)*F102 -> 0.10305893 | G103: =(G3-H3)/(G2-H2)*G102 -> 0.18505339 | H103: =(H3-I3)/(H2-I2)*H102 -> 0.19706225
A104: 投资 | D104: =(D4-E4)/(D2-E2)*D102 -> 0.033554322 | E104: =(E4-F4)/(E2-F2)*E102 -> 0.05171497 | F104: =(F4-G4)/(F2-G2)*F102 -> 0.030972922 | G104: =(G4-H4)/(G2-H2)*G102 -> 0.01355032 | H104: =(H4-I4)/(H2-I2)*H102 -> 0.0021143456
A105: 运营资产 | D105: =(D5-E5)/(D2-E2)*D102 -> -0.0023610537 | E105: =(E5-F5)/(E2-F2)*E102 -> 0.0094313865 | F105: =(F5-G5)/(F2-G2)*F102 -> 0.010779034 | G105: =(G5-H5)/(G2-H2)*G102 -> 0.0045685833 | H105: =(H5-I5)/(H2-I2)*H102 -> 0.011990198
A106: 长期资产 | D106: =(D9-E9)/(D2-E2)*D102 -> 0.0059117491 | E106: =(E9-F9)/(E2-F2)*E102 -> 0.0066937097 | F106: =(F9-G9)/(F2-G2)*F102 -> 0.01172651 | G106: =(G9-H9)/(G2-H2)*G102 -> 0.021707437 | H106: =(H9-I9)/(H2-I2)*H102 -> 0.032491047
A107: 权益YoY | D107: =D14/E14-1 -> 0.14141907 | E107: =E14/F14-1 -> 0.13879984 | F107: =F14/G14-1 -> 0.13086816 | G107: =G14/H14-1 -> 0.12906818 | H107: =H14/I14-1 -> 0.13549183
A108: 资本投入 | D108: =(D15-E15)/(D14-E14)*D107 -> 0.016344638 | E108: =(E15-F15)/(E14-F14)*E107 -> 0.026897851 | F108: =(F15-G15)/(F14-G14)*F107 -> 0.024978782 | G108: =(G15-H15)/(G14-H14)*G107 -> 0.015326512 | H108: =(H15-I15)/(H14-I14)*H107 -> 0.008841917
A109: 未分配利润 | D109: =(D16-E16)/(D14-E14)*D107 -> 0.12059195 | E109: =(E16-F16)/(E14-F14)*E107 -> 0.10638311 | F109: =(F16-G16)/(F14-G14)*F107 -> 0.09625549 | G109: =(G16-H16)/(G14-H14)*G107 -> 0.10554999 | H109: =(H16-I16)/(H14-I14)*H107 -> 0.11991188
A110: 负债YoY | D110: =D10/E10-1 -> 0.13198009 | E110: =E10/F10-1 -> 0.21327663 | F110: =F10/G10-1 -> 0.23202978 | G110: =G10/H10-1 -> 0.63223141 | H110: =H10/I10-1 -> 1.0901925
A111: 预收 | D111: =(D11-E11)/(D10-E10)*D110 -> 0.14524815 | E111: =(E11-F11)/(E10-F10)*E110 -> 0.13990307 | F111: =(F11-G11)/(F10-G10)*F110 -> 0.17173312 | G111: =(G11-H11)/(G10-H10)*G110 -> 0.41742195 | H111: =(H11-I11)/(H10-I10)*H110 -> 1.1834643
...
